{
    "place_id": "ChIJHY64qJmpVogRng7cIsBr6nc",
    "place_name": "Heart 2 Heart Bakery & Cafe",
    "details": {
        "place_name": "",
        "place_id": "__NO_PLACE_FOUND__",
        "google_maps_url": "https://maps.google.com/?cid=",
        "website": "",
        "address": "",
        "description": "",
        "purchase_required": "Unsure",
        "parking": [
            "Unsure"
        ],
        "latitude": null,
        "longitude": null,
        "raw_data": {
            "query": "ChIJHY64qJmpVogRng7cIsBr6nc",
            "place_id": "__NO_PLACE_FOUND__",
            "google_id": "__NO_PLACE_FOUND__",
            "reviews_data": []
        }
    },
    "reviews": {
        "place_id": "ChIJHY64qJmpVogRng7cIsBr6nc",
        "message": "",
        "reviews_data": [
            {
                "google_id": "0x8856a999a8b88e1d:0x77ea6bc022dc0e9e",
                "review_id": "Ci9DQUlRQUNvZENodHljRjlvT2xVemVESkNUVmhXVTJOcVRGSmllVzVGVDFSR2VGRRAB",
                "review_pagination_id": "CAESY0NBRVFBUnBFUTJwRlNVRlNTWEJEWjI5QlVEY3lSMmRoVWxnNGJGOWZSV2hEVUZKTFJsaFRObTh5UnpKWGNsQlBPRUZCUVVGQlIyZHVPVEpwVFVOaFFuQkdabmxWV1VGRFNVRQ==",
                "author_link": "https://www.google.com/maps/contrib/114622031339035346463?hl=en",
                "author_title": "Charles Panther",
                "author_id": "114622031339035346463",
                "author_image": "https://lh3.googleusercontent.com/a-/ALV-UjXBJDgRQfIPVtV94XSgElwF1NxGM2kMM_bfw-GESzNsX4_wstaY=s120-c-rp-mo-br100",
                "author_reviews_count": 1,
                "author_ratings_count": 0,
                "review_text": "Had a great time at the jazz night!!  What a great place--cant wait to go back!!",
                "review_img_urls": null,
                "review_img_url": null,
                "review_questions": {
                    "Food": "5",
                    "Service": "5",
                    "Atmosphere": "5"
                },
                "review_photo_ids": null,
                "owner_answer": null,
                "owner_answer_timestamp": null,
                "owner_answer_timestamp_datetime_utc": null,
                "review_link": "https://www.google.com/maps/reviews/data=!4m8!14m7!1m6!2m5!1sCi9DQUlRQUNvZENodHljRjlvT2xVemVESkNUVmhXVTJOcVRGSmllVzVGVDFSR2VGRRAB!2m1!1s0x0:0x77ea6bc022dc0e9e!3m1!1s2@1:CAIQACodChtycF9oOlUzeDJCTVhWU2NqTFJieW5FT1RGeFE%7C%7C?hl=en",
                "review_rating": 5,
                "review_timestamp": 1751905894,
                "review_datetime_utc": "07/07/2025 16:31:34",
                "review_likes": null,
                "reviews_id": "8640837308026457758"
            },
            {
                "google_id": "0x8856a999a8b88e1d:0x77ea6bc022dc0e9e",
                "review_id": "ChZDSUhNMG9nS0VJM3UxWlhIOXA3cVd3EAE",
                "review_pagination_id": "CAESY0NBRVFBaHBFUTJwRlNVRlNTWEJEWjI5QlVEY3lSMnMyV1hGTk9WOWZSV2hCUm5KNlNtcDNhR1paV0VoT2FuaGxiMEZCUVVGQlIyZHVPVEptVFVOaFZIQnBiM293V1VGRFNVRQ==",
                "author_link": "https://www.google.com/maps/contrib/117358079917402353280?hl=en",
                "author_title": "Maria Alessi",
                "author_id": "117358079917402353280",
                "author_image": "https://lh3.googleusercontent.com/a-/ALV-UjWqBfurQ-z5TRMGTqNSru39ZnVHprhjCDR1mTh0I3LPLyp0Te_n=s120-c-rp-mo-br100",
                "author_reviews_count": 1,
                "author_ratings_count": 0,
                "review_text": "Marilyn made us the most delicious carrot cake for our wedding! Couldn't have asked for better ^-^",
                "review_img_urls": null,
                "review_img_url": null,
                "review_questions": null,
                "review_photo_ids": null,
                "owner_answer": null,
                "owner_answer_timestamp": null,
                "owner_answer_timestamp_datetime_utc": null,
                "review_link": "https://www.google.com/maps/reviews/data=!4m8!14m7!1m6!2m5!1sChZDSUhNMG9nS0VJM3UxWlhIOXA3cVd3EAE!2m1!1s0x0:0x77ea6bc022dc0e9e!3m1!1s2@1:CIHM0ogKEI3u1ZXH9p7qWw%7C%7C?hl=en",
                "review_rating": 5,
                "review_timestamp": 1747072146,
                "review_datetime_utc": "05/12/2025 17:49:06",
                "review_likes": null,
                "reviews_id": "8640837308026457758"
            },
            {
                "google_id": "0x8856a999a8b88e1d:0x77ea6bc022dc0e9e",
                "review_id": "ChdDSUhNMG9nS0VJQ0FnTUNJaTR1VTh3RRAB",
                "review_pagination_id": "CAESY0NBRVFBeHBFUTJwRlNVRlNTWEJEWjI5QlVEY3lSMjR0U2pGUGFsOWZSV2hFYkVOS04wNTZRWFZvUjJ0RFh6VTJVVUZCUVVGQlIyZHVPVEpUTkVOaFpqUnVWVFpOV1VGRFNVRQ==",
                "author_link": "https://www.google.com/maps/contrib/115129061397536287529?hl=en",
                "author_title": "Chloe Campbell",
                "author_id": "115129061397536287529",
                "author_image": "https://lh3.googleusercontent.com/a-/ALV-UjXLyZC0KZgmthdImiy3zGdqoe4Rzq8h8M95rNvMzGtd6PoGdTSgMw=s120-c-rp-mo-ba5-br100",
                "author_reviews_count": 11,
                "author_ratings_count": 255,
                "review_text": "I was lucky enough to get to try three of the pound cakes available: Five Flavor, Chocolate, and Strawberry. *Absolutely* delicious!! These are old-fashioned pound cakes, dense in a good way, sweet and not over the top, and the icing is too good, especially on the chocolate. Do yourself a favor and stop by here! I can't wait to try some of the coconut cake.",
                "review_img_urls": null,
                "review_img_url": null,
                "review_questions": {
                    "Service": "5",
                    "Meal type": "Other",
                    "Food": "5",
                    "Recommended dishes": "German Chocolate Cake, Five Flavor Pound Cake"
                },
                "review_photo_ids": null,
                "owner_answer": null,
                "owner_answer_timestamp": null,
                "owner_answer_timestamp_datetime_utc": null,
                "review_link": "https://www.google.com/maps/reviews/data=!4m8!14m7!1m6!2m5!1sChdDSUhNMG9nS0VJQ0FnTUNJaTR1VTh3RRAB!2m1!1s0x0:0x77ea6bc022dc0e9e!3m1!1s2@1:CIHM0ogKEICAgMCIi4uU8wE%7C%7C?hl=en",
                "review_rating": 5,
                "review_timestamp": 1743787699,
                "review_datetime_utc": "04/04/2025 17:28:19",
                "review_likes": null,
                "reviews_id": "8640837308026457758"
            },
            {
                "google_id": "0x8856a999a8b88e1d:0x77ea6bc022dc0e9e",
                "review_id": "ChdDSUhNMG9nS0VJQ0FnSUM5MTlYRmdBRRAB",
                "review_pagination_id": "CAESY0NBRVFCQnBFUTJwRlNVRlNTWEJEWjI5QlVEY3lTRWhXUVhsS2JGOWZSV2hEUmxObE5rUTRXamR3T0c1Tk1GbFlWVUZCUVVGQlIyZHVPVGRYTUVOalpGVkVTVzFWV1VGRFNVRQ==",
                "author_link": "https://www.google.com/maps/contrib/101460554926270953926?hl=en",
                "author_title": "Arnet Diggs",
                "author_id": "101460554926270953926",
                "author_image": "https://lh3.googleusercontent.com/a-/ALV-UjW0NmvIBgOA5ABN16N4HAQdkquCZflctru8BQ6XofZci__JkC0j=s120-c-rp-mo-ba4-br100",
                "author_reviews_count": 69,
                "author_ratings_count": 18,
                "review_text": "Excellent baked goods and live entertainment \ud83d\udc4c",
                "review_img_urls": null,
                "review_img_url": null,
                "review_questions": {
                    "Food": "5",
                    "Service": "5",
                    "Atmosphere": "5",
                    "Recommended dishes": "Pistachio Coffee Cake, Butter Coffee Cake, Italian Velvet Cake, Coconut Cake, Five Flavor Pound Cake, Caramel Cake"
                },
                "review_photo_ids": null,
                "owner_answer": null,
                "owner_answer_timestamp": null,
                "owner_answer_timestamp_datetime_utc": null,
                "review_link": "https://www.google.com/maps/reviews/data=!4m8!14m7!1m6!2m5!1sChdDSUhNMG9nS0VJQ0FnSUM5MTlYRmdBRRAB!2m1!1s0x0:0x77ea6bc022dc0e9e!3m1!1s2@1:CIHM0ogKEICAgIC919XFgAE%7C%7C?hl=en",
                "review_rating": 5,
                "review_timestamp": 1710118198,
                "review_datetime_utc": "03/11/2024 00:49:58",
                "review_likes": null,
                "reviews_id": "8640837308026457758"
            },
            {
                "google_id": "0x8856a999a8b88e1d:0x77ea6bc022dc0e9e",
                "review_id": "ChdDSUhNMG9nS0VJQ0FnSUNsM1k2QzhRRRAB",
                "review_pagination_id": "CAESY0NBRVFCUnBFUTJwRlNVRlNTWEJEWjI5QlVEY3lTRkE0VUVKYVZWOWZSV2hEY25aVlJqTjNka3BpVFdoUVF6SnNTVUZCUVVGQlIyZHVPVGxzYjBOalgzYzRSbXhSV1VGRFNVRQ==",
                "author_link": "https://www.google.com/maps/contrib/102496730204424792280?hl=en",
                "author_title": "Ronald Potts",
                "author_id": "102496730204424792280",
                "author_image": "https://lh3.googleusercontent.com/a-/ALV-UjW7-UDMPE5kDT9HtBrDjrKSVdST1BisGdmHaA1xKeXwcpYXsBKc=s120-c-rp-mo-ba3-br100",
                "author_reviews_count": 25,
                "author_ratings_count": 28,
                "review_text": "Always a great experience!",
                "review_img_urls": null,
                "review_img_url": null,
                "review_questions": {
                    "Meal type": "Other",
                    "Price per person": "$30\u201350",
                    "Recommended dishes": "Butter Coffee Cake"
                },
                "review_photo_ids": null,
                "owner_answer": null,
                "owner_answer_timestamp": null,
                "owner_answer_timestamp_datetime_utc": null,
                "review_link": "https://www.google.com/maps/reviews/data=!4m8!14m7!1m6!2m5!1sChdDSUhNMG9nS0VJQ0FnSUNsM1k2QzhRRRAB!2m1!1s0x0:0x77ea6bc022dc0e9e!3m1!1s2@1:CIHM0ogKEICAgICl3Y6C8QE%7C%7C?hl=en",
                "review_rating": 5,
                "review_timestamp": 1700870220,
                "review_datetime_utc": "11/24/2023 23:57:00",
                "review_likes": null,
                "reviews_id": "8640837308026457758"
            },
            {
                "google_id": "0x8856a999a8b88e1d:0x77ea6bc022dc0e9e",
                "review_id": "ChdDSUhNMG9nS0VJQ0FnSUR4NWJfVmp3RRAB",
                "review_pagination_id": "CAESY0NBRVFCaHBFUTJwRlNVRlNTWEJEWjI5QlVEY3lTR1JSU1ZKdVdWOWZSV2hCZVVOUWFFOWhNalpRYUhsUFdsVktNRUZCUVVGQlIyZHVPVE5MYzBOa01VRm9SMlJuV1VGRFNVRQ==",
                "author_link": "https://www.google.com/maps/contrib/106594483168606746470?hl=en",
                "author_title": "Felecia Arrington",
                "author_id": "106594483168606746470",
                "author_image": "https://lh3.googleusercontent.com/a-/ALV-UjWPMeK-MnU50Op0SMM1Ru7uU-jrRovvijX15X7La28Xe40-pW-g=s120-c-rp-mo-ba3-br100",
                "author_reviews_count": 32,
                "author_ratings_count": 1,
                "review_text": "For those that did not want to attend or could not for various reasons (I asked several folk) this joint here is a repeat...terrr!! Been knowing of this establishment for quite some time but finally getting here!\nIt's owner Marilyn and her hubby are making it work. And yall it's worth the $35. She can BAKE! Her desserts were scrumptious and succulent. I had the pistachio swirl nut cake. One dessert and unlimited beverages are available. Assortment of Tazo teas. Several coffee selections. Reg water or perrier, lemonade, tea. Extra dessert in house or to go are $5-6. No more than you pay at any other restaurant. I got to meet ladies my age. Fellowship and listen to some bomb jazz by \"The Groove Master\" $35...WHAT? I've paid x2 as much to hear jazz & got nothing to eat or drink w/ cost of ticket. Various artist play on select Sundays.  Support this Black couples business yall. It's a cute lil quaint and cozy joint. Feels like The Color Purple Harpos Juke Joint but on a 21st century scale...its clean, perfectly decorated. Nice and charming seating. Holds about 50 folk tops...so if u dislike crowds but u love jazz...this here is it!!!\n#oh yea\n#illbeback",
                "review_img_urls": null,
                "review_img_url": null,
                "review_questions": null,
                "review_photo_ids": null,
                "owner_answer": null,
                "owner_answer_timestamp": null,
                "owner_answer_timestamp_datetime_utc": null,
                "review_link": "https://www.google.com/maps/reviews/data=!4m8!14m7!1m6!2m5!1sChdDSUhNMG9nS0VJQ0FnSUR4NWJfVmp3RRAB!2m1!1s0x0:0x77ea6bc022dc0e9e!3m1!1s2@1:CIHM0ogKEICAgIDx5b_VjwE%7C%7C?hl=en",
                "review_rating": 5,
                "review_timestamp": 1686577800,
                "review_datetime_utc": "06/12/2023 13:50:00",
                "review_likes": null,
                "reviews_id": "8640837308026457758"
            },
            {
                "google_id": "0x8856a999a8b88e1d:0x77ea6bc022dc0e9e",
                "review_id": "ChZDSUhNMG9nS0VJQ0FnSUR4cVBtSEZ3EAE",
                "review_pagination_id": "CAESY0NBRVFCeHBFUTJwRlNVRlNTWEJEWjI5QlVEY3lTR1ZOTUd4U1FsOWZSV2hDZURoUk9YcFFaUzF0ZHpaelZrOXVPRUZCUVVGQlIyZHVPVFpUVFVOa05IcFRWa1ZGV1VGRFNVRQ==",
                "author_link": "https://www.google.com/maps/contrib/100484754805474272476?hl=en",
                "author_title": "Lester Evans",
                "author_id": "100484754805474272476",
                "author_image": "https://lh3.googleusercontent.com/a/ACg8ocKZsFjJqkxbpwPYvEeMUZfZSSp8dUKJ9siVKNb8avnaznzQcg=s120-c-rp-mo-ba5-br100",
                "author_reviews_count": 176,
                "author_ratings_count": 90,
                "review_text": "Great coffee and dessert in a beautifully decorated place. Cakes, cookies and cobbler.",
                "review_img_urls": null,
                "review_img_url": null,
                "review_questions": null,
                "review_photo_ids": null,
                "owner_answer": null,
                "owner_answer_timestamp": null,
                "owner_answer_timestamp_datetime_utc": null,
                "review_link": "https://www.google.com/maps/reviews/data=!4m8!14m7!1m6!2m5!1sChZDSUhNMG9nS0VJQ0FnSUR4cVBtSEZ3EAE!2m1!1s0x0:0x77ea6bc022dc0e9e!3m1!1s2@1:CIHM0ogKEICAgIDxqPmHFw%7C%7C?hl=en",
                "review_rating": 5,
                "review_timestamp": 1685559552,
                "review_datetime_utc": "05/31/2023 18:59:12",
                "review_likes": null,
                "reviews_id": "8640837308026457758"
            },
            {
                "google_id": "0x8856a999a8b88e1d:0x77ea6bc022dc0e9e",
                "review_id": "ChZDSUhNMG9nS0VJQ0FnSUQtaUtiaVJnEAE",
                "review_pagination_id": "CAESY0NBRVFDQnBFUTJwRlNVRlNTWEJEWjI5QlVEY3lTR3R1YkdWNGNsOWZSV2hEVTJRdGQycE1hMVpYWWsxU09EZ3lXVUZCUVVGQlIyZHVPVE56YTBObFUyVldOMGR6V1VGRFNVRQ==",
                "author_link": "https://www.google.com/maps/contrib/102775930488372505121?hl=en",
                "author_title": "Regina Freeman",
                "author_id": "102775930488372505121",
                "author_image": "https://lh3.googleusercontent.com/a/ACg8ocKZKj_rlqVlO_Z9kGc5Pea4HHZHqVzG7wspPQ7KTE3yCpZBSg=s120-c-rp-mo-ba4-br100",
                "author_reviews_count": 148,
                "author_ratings_count": 4,
                "review_text": "Phenomenal!!! The band, the hospitality and the desserts were all awesome!!! Can't wait to return! Marilyn and Sam are treasures with in the community!",
                "review_img_urls": null,
                "review_img_url": null,
                "review_questions": null,
                "review_photo_ids": null,
                "owner_answer": null,
                "owner_answer_timestamp": null,
                "owner_answer_timestamp_datetime_utc": null,
                "review_link": "https://www.google.com/maps/reviews/data=!4m8!14m7!1m6!2m5!1sChZDSUhNMG9nS0VJQ0FnSUQtaUtiaVJnEAE!2m1!1s0x0:0x77ea6bc022dc0e9e!3m1!1s2@1:CIHM0ogKEICAgID-iKbiRg%7C%7C?hl=en",
                "review_rating": 5,
                "review_timestamp": 1678668075,
                "review_datetime_utc": "03/13/2023 00:41:15",
                "review_likes": null,
                "reviews_id": "8640837308026457758"
            },
            {
                "google_id": "0x8856a999a8b88e1d:0x77ea6bc022dc0e9e",
                "review_id": "ChZDSUhNMG9nS0VJQ0FnSUNZcWViTGJBEAE",
                "review_pagination_id": "CAESY0NBRVFDUnBFUTJwRlNVRlNTWEJEWjI5QlVEY3lTbGhwUmxaZkxWOWZSV2hDZEhGVWRqTTRkWE42YjFVMVkyMW1WVUZCUVVGQlIyZHVPVFJGWTBOc1pVbFdXRjgwV1VGRFNVRQ==",
                "author_link": "https://www.google.com/maps/contrib/116087215697194378299?hl=en",
                "author_title": "Jessica Vickers",
                "author_id": "116087215697194378299",
                "author_image": "https://lh3.googleusercontent.com/a-/ALV-UjV_M19qBJ5xPDLfZrFLKraPmOCa54kV_fSfXjpr6F1weRjlS6U1=s120-c-rp-mo-ba2-br100",
                "author_reviews_count": 20,
                "author_ratings_count": 19,
                "review_text": "Marilyn is the sweetest woman I ever met. And goodness can she bake! Highly recommend! Cute and cozy space!",
                "review_img_urls": null,
                "review_img_url": null,
                "review_questions": null,
                "review_photo_ids": null,
                "owner_answer": null,
                "owner_answer_timestamp": null,
                "owner_answer_timestamp_datetime_utc": null,
                "review_link": "https://www.google.com/maps/reviews/data=!4m8!14m7!1m6!2m5!1sChZDSUhNMG9nS0VJQ0FnSUNZcWViTGJBEAE!2m1!1s0x0:0x77ea6bc022dc0e9e!3m1!1s2@1:CIHM0ogKEICAgICYqebLbA%7C%7C?hl=en",
                "review_rating": 5,
                "review_timestamp": 1555280076,
                "review_datetime_utc": "04/14/2019 22:14:36",
                "review_likes": null,
                "reviews_id": "8640837308026457758"
            },
            {
                "google_id": "0x8856a999a8b88e1d:0x77ea6bc022dc0e9e",
                "review_id": "ChdDSUhNMG9nS0VJQ0FnSURvb192bjZ3RRAB",
                "review_pagination_id": "CAESY0NBRVFDaHBFUTJwRlNVRlNTWEJEWjI5QlVEY3lTbHB1VUd4emExOWZSV2hEUlVGdGVHTlhibGg0WjIwelgzRktTVUZCUVVGQlIyZHVPVGhoWjBOc2JXTXRWM2xSV1VGRFNVRQ==",
                "author_link": "https://www.google.com/maps/contrib/101969898622246436553?hl=en",
                "author_title": "Bevi C",
                "author_id": "101969898622246436553",
                "author_image": "https://lh3.googleusercontent.com/a/ACg8ocKmXNT4g2kxloRkIKXqaUNU5bA3sB7hdQ8692uGOVA0O0BR5A=s120-c-rp-mo-ba4-br100",
                "author_reviews_count": 121,
                "author_ratings_count": 38,
                "review_text": "Very nice cozy spot delicious pound cake",
                "review_img_urls": null,
                "review_img_url": null,
                "review_questions": null,
                "review_photo_ids": null,
                "owner_answer": null,
                "owner_answer_timestamp": null,
                "owner_answer_timestamp_datetime_utc": null,
                "review_link": "https://www.google.com/maps/reviews/data=!4m8!14m7!1m6!2m5!1sChdDSUhNMG9nS0VJQ0FnSURvb192bjZ3RRAB!2m1!1s0x0:0x77ea6bc022dc0e9e!3m1!1s2@1:CIHM0ogKEICAgIDoo_vn6wE%7C%7C?hl=en",
                "review_rating": 4,
                "review_timestamp": 1553046021,
                "review_datetime_utc": "03/20/2019 01:40:21",
                "review_likes": null,
                "reviews_id": "8640837308026457758"
            },
            {
                "google_id": "0x8856a999a8b88e1d:0x77ea6bc022dc0e9e",
                "review_id": "ChdDSUhNMG9nS0VJQ0FnSURvanI3d2pRRRAB",
                "review_pagination_id": "CAESY0NBRVFDeHBFUTJwRlNVRlNTWEJEWjI5QlVEY3lTbG80TlhONGVWOWZSV2hFYWpRemRIbHZaM28xVERrdGN5MWhUVUZCUVVGQlIyZHVPVGwzWjBOc2JucHRla2hKV1VGRFNVRQ==",
                "author_link": "https://www.google.com/maps/contrib/114958302673060580184?hl=en",
                "author_title": "Freda Dumas",
                "author_id": "114958302673060580184",
                "author_image": "https://lh3.googleusercontent.com/a-/ALV-UjW2HDrke5nSrZKGbbrHANzNzC8lnS7He8mdYG89QZlYnZ0ZWLk_=s120-c-rp-mo-ba4-br100",
                "author_reviews_count": 98,
                "author_ratings_count": 7,
                "review_text": "Every single item is amazing!",
                "review_img_urls": null,
                "review_img_url": null,
                "review_questions": null,
                "review_photo_ids": null,
                "owner_answer": null,
                "owner_answer_timestamp": null,
                "owner_answer_timestamp_datetime_utc": null,
                "review_link": "https://www.google.com/maps/reviews/data=!4m8!14m7!1m6!2m5!1sChdDSUhNMG9nS0VJQ0FnSURvanI3d2pRRRAB!2m1!1s0x0:0x77ea6bc022dc0e9e!3m1!1s2@1:CIHM0ogKEICAgIDojr7wjQE%7C%7C?hl=en",
                "review_rating": 5,
                "review_timestamp": 1552682660,
                "review_datetime_utc": "03/15/2019 20:44:20",
                "review_likes": null,
                "reviews_id": "8640837308026457758"
            },
            {
                "google_id": "0x8856a999a8b88e1d:0x77ea6bc022dc0e9e",
                "review_id": "ChZDSUhNMG9nS0VJQ0FnSUNvaWFfWEZ3EAE",
                "review_pagination_id": "CAESY0NBRVFEQnBFUTJwRlNVRlNTWEJEWjI5QlVEY3lTbUo2Wnpkc2NWOWZSV2hCUW5ScFNsUkNZVGxQWDBSVmJXVnZiMEZCUVVGQlIyZHVPUzF5VlVOc2RrOUVkVmR2V1VGRFNVRQ==",
                "author_link": "https://www.google.com/maps/contrib/105925618492183328612?hl=en",
                "author_title": "Keith Caldwell",
                "author_id": "105925618492183328612",
                "author_image": "https://lh3.googleusercontent.com/a/ACg8ocIkfqmZiJskpq6d6v9nJa0IXauc3RbDrLcRnIJA0zojK7WzOw=s120-c-rp-mo-br100",
                "author_reviews_count": 1,
                "author_ratings_count": 1,
                "review_text": "The cakes are awesome  .",
                "review_img_urls": null,
                "review_img_url": null,
                "review_questions": null,
                "review_photo_ids": null,
                "owner_answer": null,
                "owner_answer_timestamp": null,
                "owner_answer_timestamp_datetime_utc": null,
                "review_link": "https://www.google.com/maps/reviews/data=!4m8!14m7!1m6!2m5!1sChZDSUhNMG9nS0VJQ0FnSUNvaWFfWEZ3EAE!2m1!1s0x0:0x77ea6bc022dc0e9e!3m1!1s2@1:CIHM0ogKEICAgICoia_XFw%7C%7C?hl=en",
                "review_rating": 5,
                "review_timestamp": 1550692664,
                "review_datetime_utc": "02/20/2019 19:57:44",
                "review_likes": null,
                "reviews_id": "8640837308026457758"
            },
            {
                "google_id": "0x8856a999a8b88e1d:0x77ea6bc022dc0e9e",
                "review_id": "ChZDSUhNMG9nS0VJQ0FnSURBMGJtWEZ3EAE",
                "review_pagination_id": "CAESY0NBRVFEaHBFUTJwRlNVRlNTWEJEWjI5QlVEY3lTblp2TlVOV01WOWZSV2hFTVdsbk5saFFVMWxuT0hGblMxUjNTVUZCUVVGQlIyZHVPVE5rWjBOdExXcHJTbGhWV1VGRFNVRQ==",
                "author_link": "https://www.google.com/maps/contrib/114373230731870878811?hl=en",
                "author_title": "Sonya Allen",
                "author_id": "114373230731870878811",
                "author_image": "https://lh3.googleusercontent.com/a/ACg8ocIbrEVB8m24MJhners7Fjq3M6N1mq9-AXiMa-3PpPDDyXRSHdZf=s120-c-rp-mo-ba3-br100",
                "author_reviews_count": 38,
                "author_ratings_count": 7,
                "review_text": "A Wonderful Environment with The Best Desserts!!! Entertainment evenings are so relaxing and a phenomenal networking. I have never been disappointed at Heart 2 Heart. Wonderful Service, Exceeds all Expectations. The name said it All. Truly Heart 2 Heart.",
                "review_img_urls": null,
                "review_img_url": null,
                "review_questions": null,
                "review_photo_ids": null,
                "owner_answer": null,
                "owner_answer_timestamp": null,
                "owner_answer_timestamp_datetime_utc": null,
                "review_link": "https://www.google.com/maps/reviews/data=!4m8!14m7!1m6!2m5!1sChZDSUhNMG9nS0VJQ0FnSURBMGJtWEZ3EAE!2m1!1s0x0:0x77ea6bc022dc0e9e!3m1!1s2@1:CIHM0ogKEICAgIDA0bmXFw%7C%7C?hl=en",
                "review_rating": 5,
                "review_timestamp": 1529396058,
                "review_datetime_utc": "06/19/2018 08:14:18",
                "review_likes": null,
                "reviews_id": "8640837308026457758"
            },
            {
                "google_id": "0x8856a999a8b88e1d:0x77ea6bc022dc0e9e",
                "review_id": "ChZDSUhNMG9nS0VJQ0FnSURRbDR2aVNBEAE",
                "review_pagination_id": "CAESY0NBRVFEeHBFUTJwRlNVRlNTWEJEWjI5QlVEY3lTakZaVlhwQ05WOWZSV2hDT0VkV1lsRndkR3gyZVVsaVZtNUdWVUZCUVVGQlIyZHVPVFJEUVVOdVZtaFVUVWhyV1VGRFNVRQ==",
                "author_link": "https://www.google.com/maps/contrib/109178168184474943631?hl=en",
                "author_title": "Louise Learson",
                "author_id": "109178168184474943631",
                "author_image": "https://lh3.googleusercontent.com/a/ACg8ocJ48Qs5QvcUcB83D8539CbiItkmQqtj54TwyH2FwrmThFm5HQ=s120-c-rp-mo-br100",
                "author_reviews_count": 12,
                "author_ratings_count": 48,
                "review_text": "Excellent venue. Desserts are super good. Music was fantastic! I recommend Heart 2 Heart to anyone who wants a relaxed atmosphere with great people.",
                "review_img_urls": null,
                "review_img_url": null,
                "review_questions": null,
                "review_photo_ids": null,
                "owner_answer": null,
                "owner_answer_timestamp": null,
                "owner_answer_timestamp_datetime_utc": null,
                "review_link": "https://www.google.com/maps/reviews/data=!4m8!14m7!1m6!2m5!1sChZDSUhNMG9nS0VJQ0FnSURRbDR2aVNBEAE!2m1!1s0x0:0x77ea6bc022dc0e9e!3m1!1s2@1:CIHM0ogKEICAgIDQl4viSA%7C%7C?hl=en",
                "review_rating": 5,
                "review_timestamp": 1523231543,
                "review_datetime_utc": "04/08/2018 23:52:23",
                "review_likes": null,
                "reviews_id": "8640837308026457758"
            },
            {
                "google_id": "0x8856a999a8b88e1d:0x77ea6bc022dc0e9e",
                "review_id": "ChdDSUhNMG9nS0VJQ0FnSURBNnVPbW13RRAB",
                "review_pagination_id": "CAESY0NBRVFFQnBFUTJwRlNVRlNTWEJEWjI5QlVEY3lTak13VDNVeWFsOWZSV2hDUVRSdVZIWXlSVW95YjFoeVRreFdaMEZCUVVGQlIyZHVPVE5oYTBOdVpsRTJOMkZOV1VGRFNVRQ==",
                "author_link": "https://www.google.com/maps/contrib/104517997624998174558?hl=en",
                "author_title": "Riva Madden",
                "author_id": "104517997624998174558",
                "author_image": "https://lh3.googleusercontent.com/a/ACg8ocKwOVGvjX5l1CyEUecZJrTjlEJjNIE-tAKd6P-7SJPLUqhJcg=s120-c-rp-mo-ba4-br100",
                "author_reviews_count": 181,
                "author_ratings_count": 1,
                "review_text": "We had a fantastic time. The Reggie Boule trio was great and the singer was a plus. I won't talk about the cake. Might I say you get a slice of your choice with the ticket price.\nMarilynn and family are wonderful sponsors.\nYou will not regret attending a session.\nWe'll be back for the next session.",
                "review_img_urls": null,
                "review_img_url": null,
                "review_questions": null,
                "review_photo_ids": null,
                "owner_answer": null,
                "owner_answer_timestamp": null,
                "owner_answer_timestamp_datetime_utc": null,
                "review_link": "https://www.google.com/maps/reviews/data=!4m8!14m7!1m6!2m5!1sChdDSUhNMG9nS0VJQ0FnSURBNnVPbW13RRAB!2m1!1s0x0:0x77ea6bc022dc0e9e!3m1!1s2@1:CIHM0ogKEICAgIDA6uOmmwE%7C%7C?hl=en",
                "review_rating": 5,
                "review_timestamp": 1520615887,
                "review_datetime_utc": "03/09/2018 17:18:07",
                "review_likes": null,
                "reviews_id": "8640837308026457758"
            },
            {
                "google_id": "0x8856a999a8b88e1d:0x77ea6bc022dc0e9e",
                "review_id": "ChZDSUhNMG9nS0VJQ0FnSURnaDZHTENREAE",
                "review_pagination_id": "CAESY0NBRVFFeHBFUTJwRlNVRlNTWEJEWjI5QlVEY3lTamxmYlMweWIxOWZSV2hCV21GQ1ZYcHVXVFpLUWpabFRrOUxiMEZCUVVGQlIyZHVPVFZ5U1VOdU15MWlOMkZuV1VGRFNVRQ==",
                "author_link": "https://www.google.com/maps/contrib/109868150193971690487?hl=en",
                "author_title": "Trainer Fletch",
                "author_id": "109868150193971690487",
                "author_image": "https://lh3.googleusercontent.com/a-/ALV-UjVDgdgCxA02UgW3CXTDgKSX0HvKaiqjteEfI6B3LP-ehwQNoYogeQ=s120-c-rp-mo-ba3-br100",
                "author_reviews_count": 31,
                "author_ratings_count": 7,
                "review_text": "This place is a hidden gem. Hands down one of the best places to visit, whether you live in Charlotte or visiting. Everyone should know about this place.",
                "review_img_urls": null,
                "review_img_url": null,
                "review_questions": null,
                "review_photo_ids": null,
                "owner_answer": null,
                "owner_answer_timestamp": null,
                "owner_answer_timestamp_datetime_utc": null,
                "review_link": "https://www.google.com/maps/reviews/data=!4m8!14m7!1m6!2m5!1sChZDSUhNMG9nS0VJQ0FnSURnaDZHTENREAE!2m1!1s0x0:0x77ea6bc022dc0e9e!3m1!1s2@1:CIHM0ogKEICAgIDgh6GLCQ%7C%7C?hl=en",
                "review_rating": 5,
                "review_timestamp": 1513982530,
                "review_datetime_utc": "12/22/2017 22:42:10",
                "review_likes": null,
                "reviews_id": "8640837308026457758"
            },
            {
                "google_id": "0x8856a999a8b88e1d:0x77ea6bc022dc0e9e",
                "review_id": "ChdDSUhNMG9nS0VJQ0FnSURRalptMXZnRRAB",
                "review_pagination_id": "CAESY0NBRVFGQnBFUTJwRlNVRlNTWEJEWjI5QlVEY3lTMFJHVmkxMVpGOWZSV2hCU0VsYU5ERkllR0puY0hOd2VYZG5VVUZCUVVGQlIyZHVPVFJhV1VOdlRWWllOalV3V1VGRFNVRQ==",
                "author_link": "https://www.google.com/maps/contrib/103739995031287422739?hl=en",
                "author_title": "Elaine Cuff",
                "author_id": "103739995031287422739",
                "author_image": "https://lh3.googleusercontent.com/a-/ALV-UjX4KVLedtFfcTHYnKkrtNmGY0SEH0pnEISrMsFWqlplA0fyUyXupA=s120-c-rp-mo-br100",
                "author_reviews_count": 4,
                "author_ratings_count": 17,
                "review_text": "Every cake and cookie I tasted was delicious. The ambience of the bakery and pleasing personality of the proprietor Marilyn is \"over the top\".",
                "review_img_urls": null,
                "review_img_url": null,
                "review_questions": null,
                "review_photo_ids": null,
                "owner_answer": null,
                "owner_answer_timestamp": null,
                "owner_answer_timestamp_datetime_utc": null,
                "review_link": "https://www.google.com/maps/reviews/data=!4m8!14m7!1m6!2m5!1sChdDSUhNMG9nS0VJQ0FnSURRalptMXZnRRAB!2m1!1s0x0:0x77ea6bc022dc0e9e!3m1!1s2@1:CIHM0ogKEICAgIDQjZm1vgE%7C%7C?hl=en",
                "review_rating": 5,
                "review_timestamp": 1508517614,
                "review_datetime_utc": "10/20/2017 16:40:14",
                "review_likes": null,
                "reviews_id": "8640837308026457758"
            },
            {
                "google_id": "0x8856a999a8b88e1d:0x77ea6bc022dc0e9e",
                "review_id": "ChdDSUhNMG9nS0VJQ0FnSUNRdjUzWGlRRRAB",
                "review_pagination_id": "CAESY0NBRVFGUnBFUTJwRlNVRlNTWEJEWjI5QlVEY3lTMGxKUkRNNU5sOWZSV2hFWVdwTFlVbExWVzFPZUZCU09ISlZjMEZCUVVGQlIyZHVPVFZLZDBOdloyZFFaak52V1VGRFNVRQ==",
                "author_link": "https://www.google.com/maps/contrib/116060595508121735343?hl=en",
                "author_title": "Shawna B",
                "author_id": "116060595508121735343",
                "author_image": "https://lh3.googleusercontent.com/a/ACg8ocJP6XjTe_TJ4pEr4VelHxsm1zoSyWKwGC0_d1ASkC24_wmHOQ=s120-c-rp-mo-ba5-br100",
                "author_reviews_count": 180,
                "author_ratings_count": 54,
                "review_text": "I had a piece of the chocolate cake. It was delicious. The prices however will keep me from making this my go to bakery. Very expensive. I'm sad.",
                "review_img_urls": null,
                "review_img_url": null,
                "review_questions": null,
                "review_photo_ids": null,
                "owner_answer": null,
                "owner_answer_timestamp": null,
                "owner_answer_timestamp_datetime_utc": null,
                "review_link": "https://www.google.com/maps/reviews/data=!4m8!14m7!1m6!2m5!1sChdDSUhNMG9nS0VJQ0FnSUNRdjUzWGlRRRAB!2m1!1s0x0:0x77ea6bc022dc0e9e!3m1!1s2@1:CIHM0ogKEICAgICQv53XiQE%7C%7C?hl=en",
                "review_rating": 4,
                "review_timestamp": 1503103320,
                "review_datetime_utc": "08/19/2017 00:42:00",
                "review_likes": null,
                "reviews_id": "8640837308026457758"
            },
            {
                "google_id": "0x8856a999a8b88e1d:0x77ea6bc022dc0e9e",
                "review_id": "ChZDSUhNMG9nS0VJQ0FnSUNnaTZldkZREAE",
                "review_pagination_id": "CAESY0NBRVFGaHBFUTJwRlNVRlNTWEJEWjI5QlVEY3lTMHM0Y25kRk9GOWZSV2hFVUdGMVgzTkhjVlJxUkZWc2N6WmtaMEZCUVVGQlIyZHVPVGRuWjBOdmNubDJRVlIzV1VGRFNVRQ==",
                "author_link": "https://www.google.com/maps/contrib/104014146909300909595?hl=en",
                "author_title": "Terry Little",
                "author_id": "104014146909300909595",
                "author_image": "https://lh3.googleusercontent.com/a-/ALV-UjWJ9yfh8dib2pNCqcNquZq_We3dsNTPsF-ZuhYKzCaDP1rZxSTX=s120-c-rp-mo-ba4-br100",
                "author_reviews_count": 228,
                "author_ratings_count": 11,
                "review_text": "A wonderful place to unwind and have coffee, tea,and desserts check her out",
                "review_img_urls": null,
                "review_img_url": null,
                "review_questions": null,
                "review_photo_ids": null,
                "owner_answer": null,
                "owner_answer_timestamp": null,
                "owner_answer_timestamp_datetime_utc": null,
                "review_link": "https://www.google.com/maps/reviews/data=!4m8!14m7!1m6!2m5!1sChZDSUhNMG9nS0VJQ0FnSUNnaTZldkZREAE!2m1!1s0x0:0x77ea6bc022dc0e9e!3m1!1s2@1:CIHM0ogKEICAgICgi6evFQ%7C%7C?hl=en",
                "review_rating": 5,
                "review_timestamp": 1500072967,
                "review_datetime_utc": "07/14/2017 22:56:07",
                "review_likes": null,
                "reviews_id": "8640837308026457758"
            },
            {
                "google_id": "0x8856a999a8b88e1d:0x77ea6bc022dc0e9e",
                "review_id": "ChZDSUhNMG9nS0VJQ0FnSUNRbFlyWlRnEAE",
                "review_pagination_id": "CAESY0NBRVFHUnBFUTJwRlNVRlNTWEJEWjI5QlVEY3lTMnBITVdaeGFsOWZSV2hFUmtORlFWSnVWRFJtYkdOa1FUTlRPRUZCUVVGQlIyZHVPVFI1T0VOeFRXSldMWEZOV1VGRFNVRQ==",
                "author_link": "https://www.google.com/maps/contrib/113678442830682288940?hl=en",
                "author_title": "Kurt Hickling",
                "author_id": "113678442830682288940",
                "author_image": "https://lh3.googleusercontent.com/a-/ALV-UjUDBqPl9axL6w4ik1d9hZe_XH9Vf81i7ggfBq2tgNRb1MZ2-AcWPg=s120-c-rp-mo-ba4-br100",
                "author_reviews_count": 112,
                "author_ratings_count": 41,
                "review_text": "Great cakes and exceptional service. Sunshine delight is my favorite cake. Best cakes in a hundred miles.",
                "review_img_urls": null,
                "review_img_url": null,
                "review_questions": null,
                "review_photo_ids": null,
                "owner_answer": null,
                "owner_answer_timestamp": null,
                "owner_answer_timestamp_datetime_utc": null,
                "review_link": "https://www.google.com/maps/reviews/data=!4m8!14m7!1m6!2m5!1sChZDSUhNMG9nS0VJQ0FnSUNRbFlyWlRnEAE!2m1!1s0x0:0x77ea6bc022dc0e9e!3m1!1s2@1:CIHM0ogKEICAgICQlYrZTg%7C%7C?hl=en",
                "review_rating": 5,
                "review_timestamp": 1474132837,
                "review_datetime_utc": "09/17/2016 17:20:37",
                "review_likes": null,
                "reviews_id": "8640837308026457758"
            },
            {
                "google_id": "0x8856a999a8b88e1d:0x77ea6bc022dc0e9e",
                "review_id": "ChdDSUhNMG9nS0VJQ0FnSUN3MXFQN3BnRRAB",
                "review_pagination_id": "CAESY0NBRVFHaHBFUTJwRlNVRlNTWEJEWjI5QlVEY3lTM1pYUm1GaFMxOWZSV2hCYXkxYVlXOXdiMGxFY0VwUk9URmxUVUZCUVVGQlIyZHVPVjloWjBOeE9WbFdjRzl2V1VGRFNVRQ==",
                "author_link": "https://www.google.com/maps/contrib/101794558110373093763?hl=en",
                "author_title": "Danielle Lester",
                "author_id": "101794558110373093763",
                "author_image": "https://lh3.googleusercontent.com/a-/ALV-UjVGS58I56JPepeWp9_HAeYRcsTiIgW3LDg4zal6bbGpjrL5Io86=s120-c-rp-mo-br100",
                "author_reviews_count": 4,
                "author_ratings_count": 0,
                "review_text": "the service is great",
                "review_img_urls": null,
                "review_img_url": null,
                "review_questions": null,
                "review_photo_ids": null,
                "owner_answer": null,
                "owner_answer_timestamp": null,
                "owner_answer_timestamp_datetime_utc": null,
                "review_link": "https://www.google.com/maps/reviews/data=!4m8!14m7!1m6!2m5!1sChdDSUhNMG9nS0VJQ0FnSUN3MXFQN3BnRRAB!2m1!1s0x0:0x77ea6bc022dc0e9e!3m1!1s2@1:CIHM0ogKEICAgICw1qP7pgE%7C%7C?hl=en",
                "review_rating": 5,
                "review_timestamp": 1460992104,
                "review_datetime_utc": "04/18/2016 15:08:24",
                "review_likes": null,
                "reviews_id": "8640837308026457758"
            },
            {
                "google_id": "0x8856a999a8b88e1d:0x77ea6bc022dc0e9e",
                "review_id": "ChdDSUhNMG9nS0VJQ0FnSUNBeS1hX2hRRRAB",
                "review_pagination_id": "CAESY0NBRVFHeHBFUTJwRlNVRlNTWEJEWjI5QlVEY3lTM1pyWHpnNVNsOWZSV2hFYjFaTFkwMHlURlExU0VKV1IzRTNjMEZCUVVGQlIyZHVPVFEzYTBOeExWUmZlakJyV1VGRFNVRQ==",
                "author_link": "https://www.google.com/maps/contrib/104336340711873508806?hl=en",
                "author_title": "Abraham Williams",
                "author_id": "104336340711873508806",
                "author_image": "https://lh3.googleusercontent.com/a-/ALV-UjV5hgw7DOl2SjRFfIpkpd6_ToP8stpek7upFHlp2pSpMRWF6kUChw=s120-c-rp-mo-ba3-br100",
                "author_reviews_count": 16,
                "author_ratings_count": 9,
                "review_text": "One trip to heart 2 heart and you'll fall in love with the cakes and the owner.  Sunshine delight is #1 in my book.",
                "review_img_urls": null,
                "review_img_url": null,
                "review_questions": null,
                "review_photo_ids": null,
                "owner_answer": null,
                "owner_answer_timestamp": null,
                "owner_answer_timestamp_datetime_utc": null,
                "review_link": "https://www.google.com/maps/reviews/data=!4m8!14m7!1m6!2m5!1sChdDSUhNMG9nS0VJQ0FnSUNBeS1hX2hRRRAB!2m1!1s0x0:0x77ea6bc022dc0e9e!3m1!1s2@1:CIHM0ogKEICAgICAy-a_hQE%7C%7C?hl=en",
                "review_rating": 5,
                "review_timestamp": 1460741877,
                "review_datetime_utc": "04/15/2016 17:37:57",
                "review_likes": null,
                "reviews_id": "8640837308026457758"
            },
            {
                "google_id": "0x8856a999a8b88e1d:0x77ea6bc022dc0e9e",
                "review_id": "ChZDSUhNMG9nS0VJQ0FnSURRcXRYNmFnEAE",
                "review_pagination_id": "CAESY0NBRVFIQnBFUTJwRlNVRlNTWEJEWjI5QlVEY3lTekJVTXpNeU5WOWZSV2hDY1doSGJUazFRMmRhTVhSNGRXOVdiMEZCUVVGQlIyZHVPUzFaUlVOeVVsQm1abUpyV1VGRFNVRQ==",
                "author_link": "https://www.google.com/maps/contrib/117763739974494367549?hl=en",
                "author_title": "suga roebuck",
                "author_id": "117763739974494367549",
                "author_image": "https://lh3.googleusercontent.com/a-/ALV-UjWtGsLZKeXIM0nlEo0lD12ANC84Amqde_3zgCH5FMuRIamTf3Y=s120-c-rp-mo-br100",
                "author_reviews_count": 1,
                "author_ratings_count": 2,
                "review_text": "Great place loving ppl",
                "review_img_urls": null,
                "review_img_url": null,
                "review_questions": null,
                "review_photo_ids": null,
                "owner_answer": null,
                "owner_answer_timestamp": null,
                "owner_answer_timestamp_datetime_utc": null,
                "review_link": "https://www.google.com/maps/reviews/data=!4m8!14m7!1m6!2m5!1sChZDSUhNMG9nS0VJQ0FnSURRcXRYNmFnEAE!2m1!1s0x0:0x77ea6bc022dc0e9e!3m1!1s2@1:CIHM0ogKEICAgIDQqtX6ag%7C%7C?hl=en",
                "review_rating": 5,
                "review_timestamp": 1455660499,
                "review_datetime_utc": "02/16/2016 22:08:19",
                "review_likes": null,
                "reviews_id": "8640837308026457758"
            },
            {
                "google_id": "0x8856a999a8b88e1d:0x77ea6bc022dc0e9e",
                "review_id": "ChZDSUhNMG9nS0VJQ0FnSURRMHRlVWJREAE",
                "review_pagination_id": "CAESY0NBRVFIUnBFUTJwRlNVRlNTWEJEWjI5QlVEY3lTekptWlhwQmNsOWZSV2hEVlZoaWFVcHNabkJUWTFnMkxVbEJhMEZCUVVGQlIyZHVPVGRKUVVOeVdqazNUVU56V1VGRFNVRQ==",
                "author_link": "https://www.google.com/maps/contrib/117931454889697432691?hl=en",
                "author_title": "Nichele McDoald",
                "author_id": "117931454889697432691",
                "author_image": "https://lh3.googleusercontent.com/a/ACg8ocK1oHYSQ40IFzYLt2gXxxdOoRH1csH5N23NM8YfiJPdoFjPWQ=s120-c-rp-mo-br100",
                "author_reviews_count": 10,
                "author_ratings_count": 0,
                "review_text": "Great atmosphere! The food was so good and service was exceptional.",
                "review_img_urls": null,
                "review_img_url": null,
                "review_questions": null,
                "review_photo_ids": null,
                "owner_answer": null,
                "owner_answer_timestamp": null,
                "owner_answer_timestamp_datetime_utc": null,
                "review_link": "https://www.google.com/maps/reviews/data=!4m8!14m7!1m6!2m5!1sChZDSUhNMG9nS0VJQ0FnSURRMHRlVWJREAE!2m1!1s0x0:0x77ea6bc022dc0e9e!3m1!1s2@1:CIHM0ogKEICAgIDQ0teUbQ%7C%7C?hl=en",
                "review_rating": 5,
                "review_timestamp": 1453318262,
                "review_datetime_utc": "01/20/2016 19:31:02",
                "review_likes": null,
                "reviews_id": "8640837308026457758"
            }
        ],
        "raw_data": {
            "query": "ChIJHY64qJmpVogRng7cIsBr6nc",
            "name": "Heart 2 Heart Bakery & Cafe",
            "name_for_emails": "Heart 2 Heart Bakery And Cafe",
            "place_id": "ChIJHY64qJmpVogRng7cIsBr6nc",
            "google_id": "0x8856a999a8b88e1d:0x77ea6bc022dc0e9e",
            "kgmid": "/g/1264581ds",
            "full_address": "18409 Old Statesville Rd, Cornelius, NC 28031, United States",
            "borough": null,
            "street": "18409 Old Statesville Rd",
            "postal_code": "28031",
            "area_service": false,
            "country_code": "US",
            "country": "United States of America",
            "city": "Cornelius",
            "us_state": "North Carolina",
            "state": "North Carolina",
            "plus_code": "867XF563+MP",
            "latitude": 35.4616322,
            "longitude": -80.8457403,
            "h3": "8944daa69d3ffff",
            "time_zone": "America/New_York",
            "popular_times": null,
            "site": null,
            "phone": "+1 704-765-1068",
            "type": "Bakery",
            "logo": null,
            "description": null,
            "typical_time_spent": null,
            "located_in": null,
            "located_google_id": null,
            "category": "Bakery",
            "subtypes": "Bakery",
            "posts": null,
            "reviews_tags": [
                "desserts",
                "pound cake",
                "tea"
            ],
            "rating": 4.9,
            "reviews": 30,
            "reviews_data": [
                {
                    "google_id": "0x8856a999a8b88e1d:0x77ea6bc022dc0e9e",
                    "review_id": "Ci9DQUlRQUNvZENodHljRjlvT2xVemVESkNUVmhXVTJOcVRGSmllVzVGVDFSR2VGRRAB",
                    "review_pagination_id": "CAESY0NBRVFBUnBFUTJwRlNVRlNTWEJEWjI5QlVEY3lSMmRoVWxnNGJGOWZSV2hEVUZKTFJsaFRObTh5UnpKWGNsQlBPRUZCUVVGQlIyZHVPVEpwVFVOaFFuQkdabmxWV1VGRFNVRQ==",
                    "author_link": "https://www.google.com/maps/contrib/114622031339035346463?hl=en",
                    "author_title": "Charles Panther",
                    "author_id": "114622031339035346463",
                    "author_image": "https://lh3.googleusercontent.com/a-/ALV-UjXBJDgRQfIPVtV94XSgElwF1NxGM2kMM_bfw-GESzNsX4_wstaY=s120-c-rp-mo-br100",
                    "author_reviews_count": 1,
                    "author_ratings_count": 0,
                    "review_text": "Had a great time at the jazz night!!  What a great place--cant wait to go back!!",
                    "review_img_urls": null,
                    "review_img_url": null,
                    "review_questions": {
                        "Food": "5",
                        "Service": "5",
                        "Atmosphere": "5"
                    },
                    "review_photo_ids": null,
                    "owner_answer": null,
                    "owner_answer_timestamp": null,
                    "owner_answer_timestamp_datetime_utc": null,
                    "review_link": "https://www.google.com/maps/reviews/data=!4m8!14m7!1m6!2m5!1sCi9DQUlRQUNvZENodHljRjlvT2xVemVESkNUVmhXVTJOcVRGSmllVzVGVDFSR2VGRRAB!2m1!1s0x0:0x77ea6bc022dc0e9e!3m1!1s2@1:CAIQACodChtycF9oOlUzeDJCTVhWU2NqTFJieW5FT1RGeFE%7C%7C?hl=en",
                    "review_rating": 5,
                    "review_timestamp": 1751905894,
                    "review_datetime_utc": "07/07/2025 16:31:34",
                    "review_likes": null,
                    "reviews_id": "8640837308026457758"
                },
                {
                    "google_id": "0x8856a999a8b88e1d:0x77ea6bc022dc0e9e",
                    "review_id": "ChZDSUhNMG9nS0VJM3UxWlhIOXA3cVd3EAE",
                    "review_pagination_id": "CAESY0NBRVFBaHBFUTJwRlNVRlNTWEJEWjI5QlVEY3lSMnMyV1hGTk9WOWZSV2hCUm5KNlNtcDNhR1paV0VoT2FuaGxiMEZCUVVGQlIyZHVPVEptVFVOaFZIQnBiM293V1VGRFNVRQ==",
                    "author_link": "https://www.google.com/maps/contrib/117358079917402353280?hl=en",
                    "author_title": "Maria Alessi",
                    "author_id": "117358079917402353280",
                    "author_image": "https://lh3.googleusercontent.com/a-/ALV-UjWqBfurQ-z5TRMGTqNSru39ZnVHprhjCDR1mTh0I3LPLyp0Te_n=s120-c-rp-mo-br100",
                    "author_reviews_count": 1,
                    "author_ratings_count": 0,
                    "review_text": "Marilyn made us the most delicious carrot cake for our wedding! Couldn't have asked for better ^-^",
                    "review_img_urls": null,
                    "review_img_url": null,
                    "review_questions": null,
                    "review_photo_ids": null,
                    "owner_answer": null,
                    "owner_answer_timestamp": null,
                    "owner_answer_timestamp_datetime_utc": null,
                    "review_link": "https://www.google.com/maps/reviews/data=!4m8!14m7!1m6!2m5!1sChZDSUhNMG9nS0VJM3UxWlhIOXA3cVd3EAE!2m1!1s0x0:0x77ea6bc022dc0e9e!3m1!1s2@1:CIHM0ogKEI3u1ZXH9p7qWw%7C%7C?hl=en",
                    "review_rating": 5,
                    "review_timestamp": 1747072146,
                    "review_datetime_utc": "05/12/2025 17:49:06",
                    "review_likes": null,
                    "reviews_id": "8640837308026457758"
                },
                {
                    "google_id": "0x8856a999a8b88e1d:0x77ea6bc022dc0e9e",
                    "review_id": "ChdDSUhNMG9nS0VJQ0FnTUNJaTR1VTh3RRAB",
                    "review_pagination_id": "CAESY0NBRVFBeHBFUTJwRlNVRlNTWEJEWjI5QlVEY3lSMjR0U2pGUGFsOWZSV2hFYkVOS04wNTZRWFZvUjJ0RFh6VTJVVUZCUVVGQlIyZHVPVEpUTkVOaFpqUnVWVFpOV1VGRFNVRQ==",
                    "author_link": "https://www.google.com/maps/contrib/115129061397536287529?hl=en",
                    "author_title": "Chloe Campbell",
                    "author_id": "115129061397536287529",
                    "author_image": "https://lh3.googleusercontent.com/a-/ALV-UjXLyZC0KZgmthdImiy3zGdqoe4Rzq8h8M95rNvMzGtd6PoGdTSgMw=s120-c-rp-mo-ba5-br100",
                    "author_reviews_count": 11,
                    "author_ratings_count": 255,
                    "review_text": "I was lucky enough to get to try three of the pound cakes available: Five Flavor, Chocolate, and Strawberry. *Absolutely* delicious!! These are old-fashioned pound cakes, dense in a good way, sweet and not over the top, and the icing is too good, especially on the chocolate. Do yourself a favor and stop by here! I can't wait to try some of the coconut cake.",
                    "review_img_urls": null,
                    "review_img_url": null,
                    "review_questions": {
                        "Service": "5",
                        "Meal type": "Other",
                        "Food": "5",
                        "Recommended dishes": "German Chocolate Cake, Five Flavor Pound Cake"
                    },
                    "review_photo_ids": null,
                    "owner_answer": null,
                    "owner_answer_timestamp": null,
                    "owner_answer_timestamp_datetime_utc": null,
                    "review_link": "https://www.google.com/maps/reviews/data=!4m8!14m7!1m6!2m5!1sChdDSUhNMG9nS0VJQ0FnTUNJaTR1VTh3RRAB!2m1!1s0x0:0x77ea6bc022dc0e9e!3m1!1s2@1:CIHM0ogKEICAgMCIi4uU8wE%7C%7C?hl=en",
                    "review_rating": 5,
                    "review_timestamp": 1743787699,
                    "review_datetime_utc": "04/04/2025 17:28:19",
                    "review_likes": null,
                    "reviews_id": "8640837308026457758"
                },
                {
                    "google_id": "0x8856a999a8b88e1d:0x77ea6bc022dc0e9e",
                    "review_id": "ChdDSUhNMG9nS0VJQ0FnSUM5MTlYRmdBRRAB",
                    "review_pagination_id": "CAESY0NBRVFCQnBFUTJwRlNVRlNTWEJEWjI5QlVEY3lTRWhXUVhsS2JGOWZSV2hEUmxObE5rUTRXamR3T0c1Tk1GbFlWVUZCUVVGQlIyZHVPVGRYTUVOalpGVkVTVzFWV1VGRFNVRQ==",
                    "author_link": "https://www.google.com/maps/contrib/101460554926270953926?hl=en",
                    "author_title": "Arnet Diggs",
                    "author_id": "101460554926270953926",
                    "author_image": "https://lh3.googleusercontent.com/a-/ALV-UjW0NmvIBgOA5ABN16N4HAQdkquCZflctru8BQ6XofZci__JkC0j=s120-c-rp-mo-ba4-br100",
                    "author_reviews_count": 69,
                    "author_ratings_count": 18,
                    "review_text": "Excellent baked goods and live entertainment \ud83d\udc4c",
                    "review_img_urls": null,
                    "review_img_url": null,
                    "review_questions": {
                        "Food": "5",
                        "Service": "5",
                        "Atmosphere": "5",
                        "Recommended dishes": "Pistachio Coffee Cake, Butter Coffee Cake, Italian Velvet Cake, Coconut Cake, Five Flavor Pound Cake, Caramel Cake"
                    },
                    "review_photo_ids": null,
                    "owner_answer": null,
                    "owner_answer_timestamp": null,
                    "owner_answer_timestamp_datetime_utc": null,
                    "review_link": "https://www.google.com/maps/reviews/data=!4m8!14m7!1m6!2m5!1sChdDSUhNMG9nS0VJQ0FnSUM5MTlYRmdBRRAB!2m1!1s0x0:0x77ea6bc022dc0e9e!3m1!1s2@1:CIHM0ogKEICAgIC919XFgAE%7C%7C?hl=en",
                    "review_rating": 5,
                    "review_timestamp": 1710118198,
                    "review_datetime_utc": "03/11/2024 00:49:58",
                    "review_likes": null,
                    "reviews_id": "8640837308026457758"
                },
                {
                    "google_id": "0x8856a999a8b88e1d:0x77ea6bc022dc0e9e",
                    "review_id": "ChdDSUhNMG9nS0VJQ0FnSUNsM1k2QzhRRRAB",
                    "review_pagination_id": "CAESY0NBRVFCUnBFUTJwRlNVRlNTWEJEWjI5QlVEY3lTRkE0VUVKYVZWOWZSV2hEY25aVlJqTjNka3BpVFdoUVF6SnNTVUZCUVVGQlIyZHVPVGxzYjBOalgzYzRSbXhSV1VGRFNVRQ==",
                    "author_link": "https://www.google.com/maps/contrib/102496730204424792280?hl=en",
                    "author_title": "Ronald Potts",
                    "author_id": "102496730204424792280",
                    "author_image": "https://lh3.googleusercontent.com/a-/ALV-UjW7-UDMPE5kDT9HtBrDjrKSVdST1BisGdmHaA1xKeXwcpYXsBKc=s120-c-rp-mo-ba3-br100",
                    "author_reviews_count": 25,
                    "author_ratings_count": 28,
                    "review_text": "Always a great experience!",
                    "review_img_urls": null,
                    "review_img_url": null,
                    "review_questions": {
                        "Meal type": "Other",
                        "Price per person": "$30\u201350",
                        "Recommended dishes": "Butter Coffee Cake"
                    },
                    "review_photo_ids": null,
                    "owner_answer": null,
                    "owner_answer_timestamp": null,
                    "owner_answer_timestamp_datetime_utc": null,
                    "review_link": "https://www.google.com/maps/reviews/data=!4m8!14m7!1m6!2m5!1sChdDSUhNMG9nS0VJQ0FnSUNsM1k2QzhRRRAB!2m1!1s0x0:0x77ea6bc022dc0e9e!3m1!1s2@1:CIHM0ogKEICAgICl3Y6C8QE%7C%7C?hl=en",
                    "review_rating": 5,
                    "review_timestamp": 1700870220,
                    "review_datetime_utc": "11/24/2023 23:57:00",
                    "review_likes": null,
                    "reviews_id": "8640837308026457758"
                },
                {
                    "google_id": "0x8856a999a8b88e1d:0x77ea6bc022dc0e9e",
                    "review_id": "ChdDSUhNMG9nS0VJQ0FnSUR4NWJfVmp3RRAB",
                    "review_pagination_id": "CAESY0NBRVFCaHBFUTJwRlNVRlNTWEJEWjI5QlVEY3lTR1JSU1ZKdVdWOWZSV2hCZVVOUWFFOWhNalpRYUhsUFdsVktNRUZCUVVGQlIyZHVPVE5MYzBOa01VRm9SMlJuV1VGRFNVRQ==",
                    "author_link": "https://www.google.com/maps/contrib/106594483168606746470?hl=en",
                    "author_title": "Felecia Arrington",
                    "author_id": "106594483168606746470",
                    "author_image": "https://lh3.googleusercontent.com/a-/ALV-UjWPMeK-MnU50Op0SMM1Ru7uU-jrRovvijX15X7La28Xe40-pW-g=s120-c-rp-mo-ba3-br100",
                    "author_reviews_count": 32,
                    "author_ratings_count": 1,
                    "review_text": "For those that did not want to attend or could not for various reasons (I asked several folk) this joint here is a repeat...terrr!! Been knowing of this establishment for quite some time but finally getting here!\nIt's owner Marilyn and her hubby are making it work. And yall it's worth the $35. She can BAKE! Her desserts were scrumptious and succulent. I had the pistachio swirl nut cake. One dessert and unlimited beverages are available. Assortment of Tazo teas. Several coffee selections. Reg water or perrier, lemonade, tea. Extra dessert in house or to go are $5-6. No more than you pay at any other restaurant. I got to meet ladies my age. Fellowship and listen to some bomb jazz by \"The Groove Master\" $35...WHAT? I've paid x2 as much to hear jazz & got nothing to eat or drink w/ cost of ticket. Various artist play on select Sundays.  Support this Black couples business yall. It's a cute lil quaint and cozy joint. Feels like The Color Purple Harpos Juke Joint but on a 21st century scale...its clean, perfectly decorated. Nice and charming seating. Holds about 50 folk tops...so if u dislike crowds but u love jazz...this here is it!!!\n#oh yea\n#illbeback",
                    "review_img_urls": null,
                    "review_img_url": null,
                    "review_questions": null,
                    "review_photo_ids": null,
                    "owner_answer": null,
                    "owner_answer_timestamp": null,
                    "owner_answer_timestamp_datetime_utc": null,
                    "review_link": "https://www.google.com/maps/reviews/data=!4m8!14m7!1m6!2m5!1sChdDSUhNMG9nS0VJQ0FnSUR4NWJfVmp3RRAB!2m1!1s0x0:0x77ea6bc022dc0e9e!3m1!1s2@1:CIHM0ogKEICAgIDx5b_VjwE%7C%7C?hl=en",
                    "review_rating": 5,
                    "review_timestamp": 1686577800,
                    "review_datetime_utc": "06/12/2023 13:50:00",
                    "review_likes": null,
                    "reviews_id": "8640837308026457758"
                },
                {
                    "google_id": "0x8856a999a8b88e1d:0x77ea6bc022dc0e9e",
                    "review_id": "ChZDSUhNMG9nS0VJQ0FnSUR4cVBtSEZ3EAE",
                    "review_pagination_id": "CAESY0NBRVFCeHBFUTJwRlNVRlNTWEJEWjI5QlVEY3lTR1ZOTUd4U1FsOWZSV2hDZURoUk9YcFFaUzF0ZHpaelZrOXVPRUZCUVVGQlIyZHVPVFpUVFVOa05IcFRWa1ZGV1VGRFNVRQ==",
                    "author_link": "https://www.google.com/maps/contrib/100484754805474272476?hl=en",
                    "author_title": "Lester Evans",
                    "author_id": "100484754805474272476",
                    "author_image": "https://lh3.googleusercontent.com/a/ACg8ocKZsFjJqkxbpwPYvEeMUZfZSSp8dUKJ9siVKNb8avnaznzQcg=s120-c-rp-mo-ba5-br100",
                    "author_reviews_count": 176,
                    "author_ratings_count": 90,
                    "review_text": "Great coffee and dessert in a beautifully decorated place. Cakes, cookies and cobbler.",
                    "review_img_urls": null,
                    "review_img_url": null,
                    "review_questions": null,
                    "review_photo_ids": null,
                    "owner_answer": null,
                    "owner_answer_timestamp": null,
                    "owner_answer_timestamp_datetime_utc": null,
                    "review_link": "https://www.google.com/maps/reviews/data=!4m8!14m7!1m6!2m5!1sChZDSUhNMG9nS0VJQ0FnSUR4cVBtSEZ3EAE!2m1!1s0x0:0x77ea6bc022dc0e9e!3m1!1s2@1:CIHM0ogKEICAgIDxqPmHFw%7C%7C?hl=en",
                    "review_rating": 5,
                    "review_timestamp": 1685559552,
                    "review_datetime_utc": "05/31/2023 18:59:12",
                    "review_likes": null,
                    "reviews_id": "8640837308026457758"
                },
                {
                    "google_id": "0x8856a999a8b88e1d:0x77ea6bc022dc0e9e",
                    "review_id": "ChZDSUhNMG9nS0VJQ0FnSUQtaUtiaVJnEAE",
                    "review_pagination_id": "CAESY0NBRVFDQnBFUTJwRlNVRlNTWEJEWjI5QlVEY3lTR3R1YkdWNGNsOWZSV2hEVTJRdGQycE1hMVpYWWsxU09EZ3lXVUZCUVVGQlIyZHVPVE56YTBObFUyVldOMGR6V1VGRFNVRQ==",
                    "author_link": "https://www.google.com/maps/contrib/102775930488372505121?hl=en",
                    "author_title": "Regina Freeman",
                    "author_id": "102775930488372505121",
                    "author_image": "https://lh3.googleusercontent.com/a/ACg8ocKZKj_rlqVlO_Z9kGc5Pea4HHZHqVzG7wspPQ7KTE3yCpZBSg=s120-c-rp-mo-ba4-br100",
                    "author_reviews_count": 148,
                    "author_ratings_count": 4,
                    "review_text": "Phenomenal!!! The band, the hospitality and the desserts were all awesome!!! Can't wait to return! Marilyn and Sam are treasures with in the community!",
                    "review_img_urls": null,
                    "review_img_url": null,
                    "review_questions": null,
                    "review_photo_ids": null,
                    "owner_answer": null,
                    "owner_answer_timestamp": null,
                    "owner_answer_timestamp_datetime_utc": null,
                    "review_link": "https://www.google.com/maps/reviews/data=!4m8!14m7!1m6!2m5!1sChZDSUhNMG9nS0VJQ0FnSUQtaUtiaVJnEAE!2m1!1s0x0:0x77ea6bc022dc0e9e!3m1!1s2@1:CIHM0ogKEICAgID-iKbiRg%7C%7C?hl=en",
                    "review_rating": 5,
                    "review_timestamp": 1678668075,
                    "review_datetime_utc": "03/13/2023 00:41:15",
                    "review_likes": null,
                    "reviews_id": "8640837308026457758"
                },
                {
                    "google_id": "0x8856a999a8b88e1d:0x77ea6bc022dc0e9e",
                    "review_id": "ChZDSUhNMG9nS0VJQ0FnSUNZcWViTGJBEAE",
                    "review_pagination_id": "CAESY0NBRVFDUnBFUTJwRlNVRlNTWEJEWjI5QlVEY3lTbGhwUmxaZkxWOWZSV2hDZEhGVWRqTTRkWE42YjFVMVkyMW1WVUZCUVVGQlIyZHVPVFJGWTBOc1pVbFdXRjgwV1VGRFNVRQ==",
                    "author_link": "https://www.google.com/maps/contrib/116087215697194378299?hl=en",
                    "author_title": "Jessica Vickers",
                    "author_id": "116087215697194378299",
                    "author_image": "https://lh3.googleusercontent.com/a-/ALV-UjV_M19qBJ5xPDLfZrFLKraPmOCa54kV_fSfXjpr6F1weRjlS6U1=s120-c-rp-mo-ba2-br100",
                    "author_reviews_count": 20,
                    "author_ratings_count": 19,
                    "review_text": "Marilyn is the sweetest woman I ever met. And goodness can she bake! Highly recommend! Cute and cozy space!",
                    "review_img_urls": null,
                    "review_img_url": null,
                    "review_questions": null,
                    "review_photo_ids": null,
                    "owner_answer": null,
                    "owner_answer_timestamp": null,
                    "owner_answer_timestamp_datetime_utc": null,
                    "review_link": "https://www.google.com/maps/reviews/data=!4m8!14m7!1m6!2m5!1sChZDSUhNMG9nS0VJQ0FnSUNZcWViTGJBEAE!2m1!1s0x0:0x77ea6bc022dc0e9e!3m1!1s2@1:CIHM0ogKEICAgICYqebLbA%7C%7C?hl=en",
                    "review_rating": 5,
                    "review_timestamp": 1555280076,
                    "review_datetime_utc": "04/14/2019 22:14:36",
                    "review_likes": null,
                    "reviews_id": "8640837308026457758"
                },
                {
                    "google_id": "0x8856a999a8b88e1d:0x77ea6bc022dc0e9e",
                    "review_id": "ChdDSUhNMG9nS0VJQ0FnSURvb192bjZ3RRAB",
                    "review_pagination_id": "CAESY0NBRVFDaHBFUTJwRlNVRlNTWEJEWjI5QlVEY3lTbHB1VUd4emExOWZSV2hEUlVGdGVHTlhibGg0WjIwelgzRktTVUZCUVVGQlIyZHVPVGhoWjBOc2JXTXRWM2xSV1VGRFNVRQ==",
                    "author_link": "https://www.google.com/maps/contrib/101969898622246436553?hl=en",
                    "author_title": "Bevi C",
                    "author_id": "101969898622246436553",
                    "author_image": "https://lh3.googleusercontent.com/a/ACg8ocKmXNT4g2kxloRkIKXqaUNU5bA3sB7hdQ8692uGOVA0O0BR5A=s120-c-rp-mo-ba4-br100",
                    "author_reviews_count": 121,
                    "author_ratings_count": 38,
                    "review_text": "Very nice cozy spot delicious pound cake",
                    "review_img_urls": null,
                    "review_img_url": null,
                    "review_questions": null,
                    "review_photo_ids": null,
                    "owner_answer": null,
                    "owner_answer_timestamp": null,
                    "owner_answer_timestamp_datetime_utc": null,
                    "review_link": "https://www.google.com/maps/reviews/data=!4m8!14m7!1m6!2m5!1sChdDSUhNMG9nS0VJQ0FnSURvb192bjZ3RRAB!2m1!1s0x0:0x77ea6bc022dc0e9e!3m1!1s2@1:CIHM0ogKEICAgIDoo_vn6wE%7C%7C?hl=en",
                    "review_rating": 4,
                    "review_timestamp": 1553046021,
                    "review_datetime_utc": "03/20/2019 01:40:21",
                    "review_likes": null,
                    "reviews_id": "8640837308026457758"
                },
                {
                    "google_id": "0x8856a999a8b88e1d:0x77ea6bc022dc0e9e",
                    "review_id": "ChdDSUhNMG9nS0VJQ0FnSURvanI3d2pRRRAB",
                    "review_pagination_id": "CAESY0NBRVFDeHBFUTJwRlNVRlNTWEJEWjI5QlVEY3lTbG80TlhONGVWOWZSV2hFYWpRemRIbHZaM28xVERrdGN5MWhUVUZCUVVGQlIyZHVPVGwzWjBOc2JucHRla2hKV1VGRFNVRQ==",
                    "author_link": "https://www.google.com/maps/contrib/114958302673060580184?hl=en",
                    "author_title": "Freda Dumas",
                    "author_id": "114958302673060580184",
                    "author_image": "https://lh3.googleusercontent.com/a-/ALV-UjW2HDrke5nSrZKGbbrHANzNzC8lnS7He8mdYG89QZlYnZ0ZWLk_=s120-c-rp-mo-ba4-br100",
                    "author_reviews_count": 98,
                    "author_ratings_count": 7,
                    "review_text": "Every single item is amazing!",
                    "review_img_urls": null,
                    "review_img_url": null,
                    "review_questions": null,
                    "review_photo_ids": null,
                    "owner_answer": null,
                    "owner_answer_timestamp": null,
                    "owner_answer_timestamp_datetime_utc": null,
                    "review_link": "https://www.google.com/maps/reviews/data=!4m8!14m7!1m6!2m5!1sChdDSUhNMG9nS0VJQ0FnSURvanI3d2pRRRAB!2m1!1s0x0:0x77ea6bc022dc0e9e!3m1!1s2@1:CIHM0ogKEICAgIDojr7wjQE%7C%7C?hl=en",
                    "review_rating": 5,
                    "review_timestamp": 1552682660,
                    "review_datetime_utc": "03/15/2019 20:44:20",
                    "review_likes": null,
                    "reviews_id": "8640837308026457758"
                },
                {
                    "google_id": "0x8856a999a8b88e1d:0x77ea6bc022dc0e9e",
                    "review_id": "ChZDSUhNMG9nS0VJQ0FnSUNvaWFfWEZ3EAE",
                    "review_pagination_id": "CAESY0NBRVFEQnBFUTJwRlNVRlNTWEJEWjI5QlVEY3lTbUo2Wnpkc2NWOWZSV2hCUW5ScFNsUkNZVGxQWDBSVmJXVnZiMEZCUVVGQlIyZHVPUzF5VlVOc2RrOUVkVmR2V1VGRFNVRQ==",
                    "author_link": "https://www.google.com/maps/contrib/105925618492183328612?hl=en",
                    "author_title": "Keith Caldwell",
                    "author_id": "105925618492183328612",
                    "author_image": "https://lh3.googleusercontent.com/a/ACg8ocIkfqmZiJskpq6d6v9nJa0IXauc3RbDrLcRnIJA0zojK7WzOw=s120-c-rp-mo-br100",
                    "author_reviews_count": 1,
                    "author_ratings_count": 1,
                    "review_text": "The cakes are awesome  .",
                    "review_img_urls": null,
                    "review_img_url": null,
                    "review_questions": null,
                    "review_photo_ids": null,
                    "owner_answer": null,
                    "owner_answer_timestamp": null,
                    "owner_answer_timestamp_datetime_utc": null,
                    "review_link": "https://www.google.com/maps/reviews/data=!4m8!14m7!1m6!2m5!1sChZDSUhNMG9nS0VJQ0FnSUNvaWFfWEZ3EAE!2m1!1s0x0:0x77ea6bc022dc0e9e!3m1!1s2@1:CIHM0ogKEICAgICoia_XFw%7C%7C?hl=en",
                    "review_rating": 5,
                    "review_timestamp": 1550692664,
                    "review_datetime_utc": "02/20/2019 19:57:44",
                    "review_likes": null,
                    "reviews_id": "8640837308026457758"
                },
                {
                    "google_id": "0x8856a999a8b88e1d:0x77ea6bc022dc0e9e",
                    "review_id": "ChZDSUhNMG9nS0VJQ0FnSURBMGJtWEZ3EAE",
                    "review_pagination_id": "CAESY0NBRVFEaHBFUTJwRlNVRlNTWEJEWjI5QlVEY3lTblp2TlVOV01WOWZSV2hFTVdsbk5saFFVMWxuT0hGblMxUjNTVUZCUVVGQlIyZHVPVE5rWjBOdExXcHJTbGhWV1VGRFNVRQ==",
                    "author_link": "https://www.google.com/maps/contrib/114373230731870878811?hl=en",
                    "author_title": "Sonya Allen",
                    "author_id": "114373230731870878811",
                    "author_image": "https://lh3.googleusercontent.com/a/ACg8ocIbrEVB8m24MJhners7Fjq3M6N1mq9-AXiMa-3PpPDDyXRSHdZf=s120-c-rp-mo-ba3-br100",
                    "author_reviews_count": 38,
                    "author_ratings_count": 7,
                    "review_text": "A Wonderful Environment with The Best Desserts!!! Entertainment evenings are so relaxing and a phenomenal networking. I have never been disappointed at Heart 2 Heart. Wonderful Service, Exceeds all Expectations. The name said it All. Truly Heart 2 Heart.",
                    "review_img_urls": null,
                    "review_img_url": null,
                    "review_questions": null,
                    "review_photo_ids": null,
                    "owner_answer": null,
                    "owner_answer_timestamp": null,
                    "owner_answer_timestamp_datetime_utc": null,
                    "review_link": "https://www.google.com/maps/reviews/data=!4m8!14m7!1m6!2m5!1sChZDSUhNMG9nS0VJQ0FnSURBMGJtWEZ3EAE!2m1!1s0x0:0x77ea6bc022dc0e9e!3m1!1s2@1:CIHM0ogKEICAgIDA0bmXFw%7C%7C?hl=en",
                    "review_rating": 5,
                    "review_timestamp": 1529396058,
                    "review_datetime_utc": "06/19/2018 08:14:18",
                    "review_likes": null,
                    "reviews_id": "8640837308026457758"
                },
                {
                    "google_id": "0x8856a999a8b88e1d:0x77ea6bc022dc0e9e",
                    "review_id": "ChZDSUhNMG9nS0VJQ0FnSURRbDR2aVNBEAE",
                    "review_pagination_id": "CAESY0NBRVFEeHBFUTJwRlNVRlNTWEJEWjI5QlVEY3lTakZaVlhwQ05WOWZSV2hDT0VkV1lsRndkR3gyZVVsaVZtNUdWVUZCUVVGQlIyZHVPVFJEUVVOdVZtaFVUVWhyV1VGRFNVRQ==",
                    "author_link": "https://www.google.com/maps/contrib/109178168184474943631?hl=en",
                    "author_title": "Louise Learson",
                    "author_id": "109178168184474943631",
                    "author_image": "https://lh3.googleusercontent.com/a/ACg8ocJ48Qs5QvcUcB83D8539CbiItkmQqtj54TwyH2FwrmThFm5HQ=s120-c-rp-mo-br100",
                    "author_reviews_count": 12,
                    "author_ratings_count": 48,
                    "review_text": "Excellent venue. Desserts are super good. Music was fantastic! I recommend Heart 2 Heart to anyone who wants a relaxed atmosphere with great people.",
                    "review_img_urls": null,
                    "review_img_url": null,
                    "review_questions": null,
                    "review_photo_ids": null,
                    "owner_answer": null,
                    "owner_answer_timestamp": null,
                    "owner_answer_timestamp_datetime_utc": null,
                    "review_link": "https://www.google.com/maps/reviews/data=!4m8!14m7!1m6!2m5!1sChZDSUhNMG9nS0VJQ0FnSURRbDR2aVNBEAE!2m1!1s0x0:0x77ea6bc022dc0e9e!3m1!1s2@1:CIHM0ogKEICAgIDQl4viSA%7C%7C?hl=en",
                    "review_rating": 5,
                    "review_timestamp": 1523231543,
                    "review_datetime_utc": "04/08/2018 23:52:23",
                    "review_likes": null,
                    "reviews_id": "8640837308026457758"
                },
                {
                    "google_id": "0x8856a999a8b88e1d:0x77ea6bc022dc0e9e",
                    "review_id": "ChdDSUhNMG9nS0VJQ0FnSURBNnVPbW13RRAB",
                    "review_pagination_id": "CAESY0NBRVFFQnBFUTJwRlNVRlNTWEJEWjI5QlVEY3lTak13VDNVeWFsOWZSV2hDUVRSdVZIWXlSVW95YjFoeVRreFdaMEZCUVVGQlIyZHVPVE5oYTBOdVpsRTJOMkZOV1VGRFNVRQ==",
                    "author_link": "https://www.google.com/maps/contrib/104517997624998174558?hl=en",
                    "author_title": "Riva Madden",
                    "author_id": "104517997624998174558",
                    "author_image": "https://lh3.googleusercontent.com/a/ACg8ocKwOVGvjX5l1CyEUecZJrTjlEJjNIE-tAKd6P-7SJPLUqhJcg=s120-c-rp-mo-ba4-br100",
                    "author_reviews_count": 181,
                    "author_ratings_count": 1,
                    "review_text": "We had a fantastic time. The Reggie Boule trio was great and the singer was a plus. I won't talk about the cake. Might I say you get a slice of your choice with the ticket price.\nMarilynn and family are wonderful sponsors.\nYou will not regret attending a session.\nWe'll be back for the next session.",
                    "review_img_urls": null,
                    "review_img_url": null,
                    "review_questions": null,
                    "review_photo_ids": null,
                    "owner_answer": null,
                    "owner_answer_timestamp": null,
                    "owner_answer_timestamp_datetime_utc": null,
                    "review_link": "https://www.google.com/maps/reviews/data=!4m8!14m7!1m6!2m5!1sChdDSUhNMG9nS0VJQ0FnSURBNnVPbW13RRAB!2m1!1s0x0:0x77ea6bc022dc0e9e!3m1!1s2@1:CIHM0ogKEICAgIDA6uOmmwE%7C%7C?hl=en",
                    "review_rating": 5,
                    "review_timestamp": 1520615887,
                    "review_datetime_utc": "03/09/2018 17:18:07",
                    "review_likes": null,
                    "reviews_id": "8640837308026457758"
                },
                {
                    "google_id": "0x8856a999a8b88e1d:0x77ea6bc022dc0e9e",
                    "review_id": "ChZDSUhNMG9nS0VJQ0FnSURnaDZHTENREAE",
                    "review_pagination_id": "CAESY0NBRVFFeHBFUTJwRlNVRlNTWEJEWjI5QlVEY3lTamxmYlMweWIxOWZSV2hCV21GQ1ZYcHVXVFpLUWpabFRrOUxiMEZCUVVGQlIyZHVPVFZ5U1VOdU15MWlOMkZuV1VGRFNVRQ==",
                    "author_link": "https://www.google.com/maps/contrib/109868150193971690487?hl=en",
                    "author_title": "Trainer Fletch",
                    "author_id": "109868150193971690487",
                    "author_image": "https://lh3.googleusercontent.com/a-/ALV-UjVDgdgCxA02UgW3CXTDgKSX0HvKaiqjteEfI6B3LP-ehwQNoYogeQ=s120-c-rp-mo-ba3-br100",
                    "author_reviews_count": 31,
                    "author_ratings_count": 7,
                    "review_text": "This place is a hidden gem. Hands down one of the best places to visit, whether you live in Charlotte or visiting. Everyone should know about this place.",
                    "review_img_urls": null,
                    "review_img_url": null,
                    "review_questions": null,
                    "review_photo_ids": null,
                    "owner_answer": null,
                    "owner_answer_timestamp": null,
                    "owner_answer_timestamp_datetime_utc": null,
                    "review_link": "https://www.google.com/maps/reviews/data=!4m8!14m7!1m6!2m5!1sChZDSUhNMG9nS0VJQ0FnSURnaDZHTENREAE!2m1!1s0x0:0x77ea6bc022dc0e9e!3m1!1s2@1:CIHM0ogKEICAgIDgh6GLCQ%7C%7C?hl=en",
                    "review_rating": 5,
                    "review_timestamp": 1513982530,
                    "review_datetime_utc": "12/22/2017 22:42:10",
                    "review_likes": null,
                    "reviews_id": "8640837308026457758"
                },
                {
                    "google_id": "0x8856a999a8b88e1d:0x77ea6bc022dc0e9e",
                    "review_id": "ChdDSUhNMG9nS0VJQ0FnSURRalptMXZnRRAB",
                    "review_pagination_id": "CAESY0NBRVFGQnBFUTJwRlNVRlNTWEJEWjI5QlVEY3lTMFJHVmkxMVpGOWZSV2hCU0VsYU5ERkllR0puY0hOd2VYZG5VVUZCUVVGQlIyZHVPVFJhV1VOdlRWWllOalV3V1VGRFNVRQ==",
                    "author_link": "https://www.google.com/maps/contrib/103739995031287422739?hl=en",
                    "author_title": "Elaine Cuff",
                    "author_id": "103739995031287422739",
                    "author_image": "https://lh3.googleusercontent.com/a-/ALV-UjX4KVLedtFfcTHYnKkrtNmGY0SEH0pnEISrMsFWqlplA0fyUyXupA=s120-c-rp-mo-br100",
                    "author_reviews_count": 4,
                    "author_ratings_count": 17,
                    "review_text": "Every cake and cookie I tasted was delicious. The ambience of the bakery and pleasing personality of the proprietor Marilyn is \"over the top\".",
                    "review_img_urls": null,
                    "review_img_url": null,
                    "review_questions": null,
                    "review_photo_ids": null,
                    "owner_answer": null,
                    "owner_answer_timestamp": null,
                    "owner_answer_timestamp_datetime_utc": null,
                    "review_link": "https://www.google.com/maps/reviews/data=!4m8!14m7!1m6!2m5!1sChdDSUhNMG9nS0VJQ0FnSURRalptMXZnRRAB!2m1!1s0x0:0x77ea6bc022dc0e9e!3m1!1s2@1:CIHM0ogKEICAgIDQjZm1vgE%7C%7C?hl=en",
                    "review_rating": 5,
                    "review_timestamp": 1508517614,
                    "review_datetime_utc": "10/20/2017 16:40:14",
                    "review_likes": null,
                    "reviews_id": "8640837308026457758"
                },
                {
                    "google_id": "0x8856a999a8b88e1d:0x77ea6bc022dc0e9e",
                    "review_id": "ChdDSUhNMG9nS0VJQ0FnSUNRdjUzWGlRRRAB",
                    "review_pagination_id": "CAESY0NBRVFGUnBFUTJwRlNVRlNTWEJEWjI5QlVEY3lTMGxKUkRNNU5sOWZSV2hFWVdwTFlVbExWVzFPZUZCU09ISlZjMEZCUVVGQlIyZHVPVFZLZDBOdloyZFFaak52V1VGRFNVRQ==",
                    "author_link": "https://www.google.com/maps/contrib/116060595508121735343?hl=en",
                    "author_title": "Shawna B",
                    "author_id": "116060595508121735343",
                    "author_image": "https://lh3.googleusercontent.com/a/ACg8ocJP6XjTe_TJ4pEr4VelHxsm1zoSyWKwGC0_d1ASkC24_wmHOQ=s120-c-rp-mo-ba5-br100",
                    "author_reviews_count": 180,
                    "author_ratings_count": 54,
                    "review_text": "I had a piece of the chocolate cake. It was delicious. The prices however will keep me from making this my go to bakery. Very expensive. I'm sad.",
                    "review_img_urls": null,
                    "review_img_url": null,
                    "review_questions": null,
                    "review_photo_ids": null,
                    "owner_answer": null,
                    "owner_answer_timestamp": null,
                    "owner_answer_timestamp_datetime_utc": null,
                    "review_link": "https://www.google.com/maps/reviews/data=!4m8!14m7!1m6!2m5!1sChdDSUhNMG9nS0VJQ0FnSUNRdjUzWGlRRRAB!2m1!1s0x0:0x77ea6bc022dc0e9e!3m1!1s2@1:CIHM0ogKEICAgICQv53XiQE%7C%7C?hl=en",
                    "review_rating": 4,
                    "review_timestamp": 1503103320,
                    "review_datetime_utc": "08/19/2017 00:42:00",
                    "review_likes": null,
                    "reviews_id": "8640837308026457758"
                },
                {
                    "google_id": "0x8856a999a8b88e1d:0x77ea6bc022dc0e9e",
                    "review_id": "ChZDSUhNMG9nS0VJQ0FnSUNnaTZldkZREAE",
                    "review_pagination_id": "CAESY0NBRVFGaHBFUTJwRlNVRlNTWEJEWjI5QlVEY3lTMHM0Y25kRk9GOWZSV2hFVUdGMVgzTkhjVlJxUkZWc2N6WmtaMEZCUVVGQlIyZHVPVGRuWjBOdmNubDJRVlIzV1VGRFNVRQ==",
                    "author_link": "https://www.google.com/maps/contrib/104014146909300909595?hl=en",
                    "author_title": "Terry Little",
                    "author_id": "104014146909300909595",
                    "author_image": "https://lh3.googleusercontent.com/a-/ALV-UjWJ9yfh8dib2pNCqcNquZq_We3dsNTPsF-ZuhYKzCaDP1rZxSTX=s120-c-rp-mo-ba4-br100",
                    "author_reviews_count": 228,
                    "author_ratings_count": 11,
                    "review_text": "A wonderful place to unwind and have coffee, tea,and desserts check her out",
                    "review_img_urls": null,
                    "review_img_url": null,
                    "review_questions": null,
                    "review_photo_ids": null,
                    "owner_answer": null,
                    "owner_answer_timestamp": null,
                    "owner_answer_timestamp_datetime_utc": null,
                    "review_link": "https://www.google.com/maps/reviews/data=!4m8!14m7!1m6!2m5!1sChZDSUhNMG9nS0VJQ0FnSUNnaTZldkZREAE!2m1!1s0x0:0x77ea6bc022dc0e9e!3m1!1s2@1:CIHM0ogKEICAgICgi6evFQ%7C%7C?hl=en",
                    "review_rating": 5,
                    "review_timestamp": 1500072967,
                    "review_datetime_utc": "07/14/2017 22:56:07",
                    "review_likes": null,
                    "reviews_id": "8640837308026457758"
                },
                {
                    "google_id": "0x8856a999a8b88e1d:0x77ea6bc022dc0e9e",
                    "review_id": "ChZDSUhNMG9nS0VJQ0FnSUNRbFlyWlRnEAE",
                    "review_pagination_id": "CAESY0NBRVFHUnBFUTJwRlNVRlNTWEJEWjI5QlVEY3lTMnBITVdaeGFsOWZSV2hFUmtORlFWSnVWRFJtYkdOa1FUTlRPRUZCUVVGQlIyZHVPVFI1T0VOeFRXSldMWEZOV1VGRFNVRQ==",
                    "author_link": "https://www.google.com/maps/contrib/113678442830682288940?hl=en",
                    "author_title": "Kurt Hickling",
                    "author_id": "113678442830682288940",
                    "author_image": "https://lh3.googleusercontent.com/a-/ALV-UjUDBqPl9axL6w4ik1d9hZe_XH9Vf81i7ggfBq2tgNRb1MZ2-AcWPg=s120-c-rp-mo-ba4-br100",
                    "author_reviews_count": 112,
                    "author_ratings_count": 41,
                    "review_text": "Great cakes and exceptional service. Sunshine delight is my favorite cake. Best cakes in a hundred miles.",
                    "review_img_urls": null,
                    "review_img_url": null,
                    "review_questions": null,
                    "review_photo_ids": null,
                    "owner_answer": null,
                    "owner_answer_timestamp": null,
                    "owner_answer_timestamp_datetime_utc": null,
                    "review_link": "https://www.google.com/maps/reviews/data=!4m8!14m7!1m6!2m5!1sChZDSUhNMG9nS0VJQ0FnSUNRbFlyWlRnEAE!2m1!1s0x0:0x77ea6bc022dc0e9e!3m1!1s2@1:CIHM0ogKEICAgICQlYrZTg%7C%7C?hl=en",
                    "review_rating": 5,
                    "review_timestamp": 1474132837,
                    "review_datetime_utc": "09/17/2016 17:20:37",
                    "review_likes": null,
                    "reviews_id": "8640837308026457758"
                },
                {
                    "google_id": "0x8856a999a8b88e1d:0x77ea6bc022dc0e9e",
                    "review_id": "ChdDSUhNMG9nS0VJQ0FnSUN3MXFQN3BnRRAB",
                    "review_pagination_id": "CAESY0NBRVFHaHBFUTJwRlNVRlNTWEJEWjI5QlVEY3lTM1pYUm1GaFMxOWZSV2hCYXkxYVlXOXdiMGxFY0VwUk9URmxUVUZCUVVGQlIyZHVPVjloWjBOeE9WbFdjRzl2V1VGRFNVRQ==",
                    "author_link": "https://www.google.com/maps/contrib/101794558110373093763?hl=en",
                    "author_title": "Danielle Lester",
                    "author_id": "101794558110373093763",
                    "author_image": "https://lh3.googleusercontent.com/a-/ALV-UjVGS58I56JPepeWp9_HAeYRcsTiIgW3LDg4zal6bbGpjrL5Io86=s120-c-rp-mo-br100",
                    "author_reviews_count": 4,
                    "author_ratings_count": 0,
                    "review_text": "the service is great",
                    "review_img_urls": null,
                    "review_img_url": null,
                    "review_questions": null,
                    "review_photo_ids": null,
                    "owner_answer": null,
                    "owner_answer_timestamp": null,
                    "owner_answer_timestamp_datetime_utc": null,
                    "review_link": "https://www.google.com/maps/reviews/data=!4m8!14m7!1m6!2m5!1sChdDSUhNMG9nS0VJQ0FnSUN3MXFQN3BnRRAB!2m1!1s0x0:0x77ea6bc022dc0e9e!3m1!1s2@1:CIHM0ogKEICAgICw1qP7pgE%7C%7C?hl=en",
                    "review_rating": 5,
                    "review_timestamp": 1460992104,
                    "review_datetime_utc": "04/18/2016 15:08:24",
                    "review_likes": null,
                    "reviews_id": "8640837308026457758"
                },
                {
                    "google_id": "0x8856a999a8b88e1d:0x77ea6bc022dc0e9e",
                    "review_id": "ChdDSUhNMG9nS0VJQ0FnSUNBeS1hX2hRRRAB",
                    "review_pagination_id": "CAESY0NBRVFHeHBFUTJwRlNVRlNTWEJEWjI5QlVEY3lTM1pyWHpnNVNsOWZSV2hFYjFaTFkwMHlURlExU0VKV1IzRTNjMEZCUVVGQlIyZHVPVFEzYTBOeExWUmZlakJyV1VGRFNVRQ==",
                    "author_link": "https://www.google.com/maps/contrib/104336340711873508806?hl=en",
                    "author_title": "Abraham Williams",
                    "author_id": "104336340711873508806",
                    "author_image": "https://lh3.googleusercontent.com/a-/ALV-UjV5hgw7DOl2SjRFfIpkpd6_ToP8stpek7upFHlp2pSpMRWF6kUChw=s120-c-rp-mo-ba3-br100",
                    "author_reviews_count": 16,
                    "author_ratings_count": 9,
                    "review_text": "One trip to heart 2 heart and you'll fall in love with the cakes and the owner.  Sunshine delight is #1 in my book.",
                    "review_img_urls": null,
                    "review_img_url": null,
                    "review_questions": null,
                    "review_photo_ids": null,
                    "owner_answer": null,
                    "owner_answer_timestamp": null,
                    "owner_answer_timestamp_datetime_utc": null,
                    "review_link": "https://www.google.com/maps/reviews/data=!4m8!14m7!1m6!2m5!1sChdDSUhNMG9nS0VJQ0FnSUNBeS1hX2hRRRAB!2m1!1s0x0:0x77ea6bc022dc0e9e!3m1!1s2@1:CIHM0ogKEICAgICAy-a_hQE%7C%7C?hl=en",
                    "review_rating": 5,
                    "review_timestamp": 1460741877,
                    "review_datetime_utc": "04/15/2016 17:37:57",
                    "review_likes": null,
                    "reviews_id": "8640837308026457758"
                },
                {
                    "google_id": "0x8856a999a8b88e1d:0x77ea6bc022dc0e9e",
                    "review_id": "ChZDSUhNMG9nS0VJQ0FnSURRcXRYNmFnEAE",
                    "review_pagination_id": "CAESY0NBRVFIQnBFUTJwRlNVRlNTWEJEWjI5QlVEY3lTekJVTXpNeU5WOWZSV2hDY1doSGJUazFRMmRhTVhSNGRXOVdiMEZCUVVGQlIyZHVPUzFaUlVOeVVsQm1abUpyV1VGRFNVRQ==",
                    "author_link": "https://www.google.com/maps/contrib/117763739974494367549?hl=en",
                    "author_title": "suga roebuck",
                    "author_id": "117763739974494367549",
                    "author_image": "https://lh3.googleusercontent.com/a-/ALV-UjWtGsLZKeXIM0nlEo0lD12ANC84Amqde_3zgCH5FMuRIamTf3Y=s120-c-rp-mo-br100",
                    "author_reviews_count": 1,
                    "author_ratings_count": 2,
                    "review_text": "Great place loving ppl",
                    "review_img_urls": null,
                    "review_img_url": null,
                    "review_questions": null,
                    "review_photo_ids": null,
                    "owner_answer": null,
                    "owner_answer_timestamp": null,
                    "owner_answer_timestamp_datetime_utc": null,
                    "review_link": "https://www.google.com/maps/reviews/data=!4m8!14m7!1m6!2m5!1sChZDSUhNMG9nS0VJQ0FnSURRcXRYNmFnEAE!2m1!1s0x0:0x77ea6bc022dc0e9e!3m1!1s2@1:CIHM0ogKEICAgIDQqtX6ag%7C%7C?hl=en",
                    "review_rating": 5,
                    "review_timestamp": 1455660499,
                    "review_datetime_utc": "02/16/2016 22:08:19",
                    "review_likes": null,
                    "reviews_id": "8640837308026457758"
                },
                {
                    "google_id": "0x8856a999a8b88e1d:0x77ea6bc022dc0e9e",
                    "review_id": "ChZDSUhNMG9nS0VJQ0FnSURRMHRlVWJREAE",
                    "review_pagination_id": "CAESY0NBRVFIUnBFUTJwRlNVRlNTWEJEWjI5QlVEY3lTekptWlhwQmNsOWZSV2hEVlZoaWFVcHNabkJUWTFnMkxVbEJhMEZCUVVGQlIyZHVPVGRKUVVOeVdqazNUVU56V1VGRFNVRQ==",
                    "author_link": "https://www.google.com/maps/contrib/117931454889697432691?hl=en",
                    "author_title": "Nichele McDoald",
                    "author_id": "117931454889697432691",
                    "author_image": "https://lh3.googleusercontent.com/a/ACg8ocK1oHYSQ40IFzYLt2gXxxdOoRH1csH5N23NM8YfiJPdoFjPWQ=s120-c-rp-mo-br100",
                    "author_reviews_count": 10,
                    "author_ratings_count": 0,
                    "review_text": "Great atmosphere! The food was so good and service was exceptional.",
                    "review_img_urls": null,
                    "review_img_url": null,
                    "review_questions": null,
                    "review_photo_ids": null,
                    "owner_answer": null,
                    "owner_answer_timestamp": null,
                    "owner_answer_timestamp_datetime_utc": null,
                    "review_link": "https://www.google.com/maps/reviews/data=!4m8!14m7!1m6!2m5!1sChZDSUhNMG9nS0VJQ0FnSURRMHRlVWJREAE!2m1!1s0x0:0x77ea6bc022dc0e9e!3m1!1s2@1:CIHM0ogKEICAgIDQ0teUbQ%7C%7C?hl=en",
                    "review_rating": 5,
                    "review_timestamp": 1453318262,
                    "review_datetime_utc": "01/20/2016 19:31:02",
                    "review_likes": null,
                    "reviews_id": "8640837308026457758"
                }
            ],
            "photos_count": 2,
            "cid": "8640837308026457758",
            "reviews_link": "https://search.google.com/local/reviews?placeid=ChIJHY64qJmpVogRng7cIsBr6nc&authuser=0&hl=en&gl=UA",
            "reviews_id": "8640837308026457758",
            "photo": "https://lh3.googleusercontent.com/gps-cs-s/AC9h4noZZu8nMmhAx85X3Nsaj9p8ywvyOBJt2QBDJHjIVuOhTVm612xwl_M8n8g6BC_o1S0Dnn6gB5GMDHrQrEqClDpquPfCx_RQCfR_g8vpjDH1DrzVRxue9Dee0fR_byZVCmcl0CdwBA=w800-h500-k-no",
            "street_view": "https://streetviewpixels-pa.googleapis.com/v1/thumbnail?panoid=YXzCR9vYyKLCziz1KszZRw&cb_client=search.gws-prod.gps&w=1600&h=1000&yaw=158.88979&pitch=0&thumbfov=100",
            "working_hours": {
                "Monday": "Closed",
                "Tuesday": "Closed",
                "Wednesday": "Closed",
                "Thursday": "10AM-5PM",
                "Friday": "10AM-5PM",
                "Saturday": "10AM-2PM",
                "Sunday": "Closed"
            },
            "working_hours_csv_compatible": "Sunday,|Monday,|Tuesday,|Wednesday,|Thursday,10AM,5PM|Friday,10AM,5PM|Saturday,10AM,2PM",
            "working_hours_old_format": "Monday:Closed|Tuesday:Closed|Wednesday:Closed|Thursday:10AM-5PM|Friday:10AM-5PM|Saturday:10AM-2PM|Sunday:Closed",
            "other_hours": null,
            "business_status": "OPERATIONAL",
            "about": {
                "Service options": {
                    "In-store pick-up": true,
                    "Takeaway": true,
                    "Delivery": false
                },
                "Accessibility": {
                    "Wheelchair-accessible car park": true,
                    "Wheelchair-accessible entrance": true,
                    "Wheelchair-accessible toilet": true
                },
                "Offerings": {
                    "Coffee": true
                },
                "Amenities": {
                    "Toilet": true
                },
                "Planning": {
                    "Quick visit": true
                },
                "Payments": {
                    "Credit cards": true,
                    "Debit cards": true,
                    "NFC mobile payments": true
                }
            },
            "range": "$$",
            "prices": null,
            "reviews_per_score": null,
            "reviews_per_score_1": null,
            "reviews_per_score_2": null,
            "reviews_per_score_3": null,
            "reviews_per_score_4": null,
            "reviews_per_score_5": null,
            "reservation_links": null,
            "booking_appointment_link": null,
            "menu_link": "http://places.singleplatform.com/heart-2-heart-bakery--cafe/menu?ref=google",
            "order_links": null,
            "owner_id": null,
            "verified": false,
            "owner_title": "Heart 2 Heart Bakery & Cafe",
            "owner_link": null,
            "location_link": "https://www.google.com/maps/place/Heart+2+Heart+Bakery+%26+Cafe/@35.4616322,-80.8457403,14z/data=!4m8!1m2!2m1!1sHeart+2+Heart+Bakery+%26+Cafe!3m4!1s0x8856a999a8b88e1d:0x77ea6bc022dc0e9e!8m2!3d35.4616322!4d-80.8457403",
            "location_reviews_link": "https://www.google.com/maps/place/Heart+2+Heart+Bakery+%26+Cafe/@35.4616322,-80.8457403,13.99z/data=!4m16!1m7!3m6!1s0x8856a999a8b88e1d:0x77ea6bc022dc0e9e!2sHeart+2+Heart+Bakery+%26+Cafe!8m2!3d35.4616322!4d-80.8457403!16s%2Fg%2F11ckvg1dmb!3m7!1s0x8856a999a8b88e1d:0x77ea6bc022dc0e9e!8m2!3d35.4616322!4d-80.8457403!9m1!1b1!16s%2Fg%2F11ckvg1dmb?entry=ttu"
        }
    },
    "photos": {
        "place_id": "ChIJHY64qJmpVogRng7cIsBr6nc",
        "message": "Photos retrieval skipped.",
        "photo_urls": []
    },
    "data_source": "OutscraperProvider",
    "last_updated": "2025-09-22T12:40:00.085732"
}