{
    "place_id": "ChIJ0y7jB9QPVIgRxBtv6daWRAw",
    "place_name": "Coffin House Coffee",
    "details": {
        "place_name": "",
        "place_id": "ChIJ0y7jB9QPVIgRxBtv6daWRAw",
        "google_maps_url": "",
        "website": "",
        "address": "",
        "description": "",
        "purchase_required": "Unsure",
        "parking": [
            "Unsure"
        ],
        "latitude": null,
        "longitude": null,
        "raw_data": {},
        "error": "Response status code: 402"
    },
    "reviews": {
        "place_id": "ChIJ0y7jB9QPVIgRxBtv6daWRAw",
        "message": "Error retrieving reviews: Response status code: 402",
        "reviews_data": []
    },
    "photos": {
        "place_id": "ChIJ0y7jB9QPVIgRxBtv6daWRAw",
        "message": "Error retrieving photos: Response status code: 402",
        "photos_data": []
    },
    "data_source": "OutscraperProvider",
    "last_updated": "2025-04-13T18:14:18.863427"
}