{
    "place_id": "ChIJ79I38fsdVIgRD0su4wT_zaw",
    "place_name": "1368 Sweet Corner Cafe | University City",
    "details": {
        "place_name": "1368 Sweet Corner Cafe",
        "place_id": "ChIJ79I38fsdVIgRD0su4wT_zaw",
        "google_maps_url": "https://maps.google.com/?cid=12451888941205703439",
        "website": "",
        "address": "9211 N Tryon St #5, Charlotte, NC 28262",
        "description": null,
        "purchase_required": "Unsure",
        "parking": [
            "Unsure"
        ],
        "latitude": 35.3123844,
        "longitude": -80.7452253,
        "raw_data": {
            "about": {
                "Service options": {
                    "Delivery": true,
                    "Dine-in": true,
                    "No-contact delivery": true,
                    "Takeout": true
                }
            },
            "address": "9211 N Tryon St #5, Charlotte, NC 28262",
            "area_service": false,
            "booking_appointment_link": null,
            "business_status": "OPERATIONAL",
            "category": "restaurants",
            "cid": "12451888941205703439",
            "city": "Charlotte",
            "country": "United States of America",
            "country_code": "US",
            "county": "University City North",
            "description": null,
            "google_id": "0x88541dfbf137d2ef:0xaccdff04e32e4b0f",
            "h3": "8944dab5233ffff",
            "kgmid": "/g/11z11cy4y7",
            "latitude": 35.3123844,
            "located_google_id": null,
            "located_in": null,
            "location_link": "https://www.google.com/maps/place/1368+Sweet+Corner+Cafe/@35.3123844,-80.7452253,14z/data=!4m8!1m2!2m1!1s1368+Sweet+Corner+Cafe!3m4!1s0x88541dfbf137d2ef:0xaccdff04e32e4b0f!8m2!3d35.3123844!4d-80.7452253",
            "location_reviews_link": "https://www.google.com/maps/place/1368+Sweet+Corner+Cafe/@35.3123844,-80.7452253,13.99z/data=!4m16!1m7!3m6!1s0x88541dfbf137d2ef:0xaccdff04e32e4b0f!2s1368+Sweet+Corner+Cafe!8m2!3d35.3123844!4d-80.7452253!16s%2Fg%2F11ckvg1dmb!3m7!1s0x88541dfbf137d2ef:0xaccdff04e32e4b0f!8m2!3d35.3123844!4d-80.7452253!9m1!1b1!16s%2Fg%2F11ckvg1dmb?entry=ttu",
            "logo": "https://lh3.googleusercontent.com/-GInoYVGXTHc/AAAAAAAAAAI/AAAAAAAAAAA/vfeoF7DrtOQ/s44-p-k-no-ns-nd/photo.jpg",
            "longitude": -80.7452253,
            "menu_link": null,
            "name": "1368 Sweet Corner Cafe",
            "name_for_emails": "1368 Sweet Corner Cafe",
            "order_links": null,
            "other_hours": null,
            "owner_id": "112959749046836881640",
            "owner_link": "https://www.google.com/maps/contrib/112959749046836881640",
            "owner_title": "1368 Sweet Corner Cafe",
            "phone": "+1 980-368-3688",
            "photo": "https://lh3.googleusercontent.com/gps-cs-s/AHVAwerQBppSicUZB_FY9QszKNCP-JT4g9caD3ohCvoYaetLODy7GwTQZl93egw1jZpfNL6wPaVA_CTAEUjwLQT4ZDY7iFst5fR78Y7hfHGqkzUzbFOFLsJfTpwpdkq7JlHs2Te7rWlygK5orok=w800-h500-k-no",
            "photos_count": 7,
            "place_id": "ChIJ79I38fsdVIgRD0su4wT_zaw",
            "plus_code": "867X8763+XW",
            "popular_times": null,
            "postal_code": "28262",
            "posts": null,
            "prices": null,
            "query": "ChIJ79I38fsdVIgRD0su4wT_zaw",
            "range": null,
            "rating": null,
            "reservation_links": null,
            "reviews": null,
            "reviews_id": null,
            "reviews_link": null,
            "reviews_per_score": null,
            "reviews_tags": null,
            "state": "North Carolina",
            "state_code": "NC",
            "street": "9211 N Tryon St #5",
            "street_view": "https://streetviewpixels-pa.googleapis.com/v1/thumbnail?panoid=oVF68STM6bhwkfmyu4mPbg&cb_client=search.gws-prod.gps&w=1600&h=1000&yaw=203.18007&pitch=0&thumbfov=100",
            "subtypes": "Vietnamese restaurant",
            "time_zone": "America/New_York",
            "type": "Vietnamese restaurant",
            "typical_time_spent": null,
            "verified": true,
            "website": "https://www.1368sweetcornercafe.com/",
            "working_hours": null,
            "working_hours_csv_compatible": null
        }
    },
    "reviews": {
        "place_id": "ChIJ79I38fsdVIgRD0su4wT_zaw",
        "message": "",
        "reviews_data": [],
        "raw_data": {
            "about": {
                "Service options": {
                    "Delivery": true,
                    "Dine-in": true,
                    "No-contact delivery": true,
                    "Takeout": true
                }
            },
            "address": "9211 N Tryon St #5, Charlotte, NC 28262",
            "area_service": false,
            "booking_appointment_link": null,
            "business_status": "OPERATIONAL",
            "category": "restaurants",
            "cid": "12451888941205703439",
            "city": "Charlotte",
            "country": "United States of America",
            "country_code": "US",
            "county": "University City North",
            "description": null,
            "google_id": "0x88541dfbf137d2ef:0xaccdff04e32e4b0f",
            "h3": "8944dab5233ffff",
            "kgmid": "/g/11z11cy4y7",
            "latitude": 35.3123844,
            "located_google_id": null,
            "located_in": null,
            "location_link": "https://www.google.com/maps/place/1368+Sweet+Corner+Cafe/@35.3123844,-80.7452253,14z/data=!4m8!1m2!2m1!1s1368+Sweet+Corner+Cafe!3m4!1s0x88541dfbf137d2ef:0xaccdff04e32e4b0f!8m2!3d35.3123844!4d-80.7452253",
            "location_reviews_link": "https://www.google.com/maps/place/1368+Sweet+Corner+Cafe/@35.3123844,-80.7452253,13.99z/data=!4m16!1m7!3m6!1s0x88541dfbf137d2ef:0xaccdff04e32e4b0f!2s1368+Sweet+Corner+Cafe!8m2!3d35.3123844!4d-80.7452253!16s%2Fg%2F11ckvg1dmb!3m7!1s0x88541dfbf137d2ef:0xaccdff04e32e4b0f!8m2!3d35.3123844!4d-80.7452253!9m1!1b1!16s%2Fg%2F11ckvg1dmb?entry=ttu",
            "logo": "https://lh3.googleusercontent.com/-GInoYVGXTHc/AAAAAAAAAAI/AAAAAAAAAAA/vfeoF7DrtOQ/s44-p-k-no-ns-nd/photo.jpg",
            "longitude": -80.7452253,
            "menu_link": null,
            "name": "1368 Sweet Corner Cafe",
            "name_for_emails": "1368 Sweet Corner Cafe",
            "order_links": null,
            "other_hours": null,
            "owner_id": "112959749046836881640",
            "owner_link": "https://www.google.com/maps/contrib/112959749046836881640",
            "owner_title": "1368 Sweet Corner Cafe",
            "phone": "+1 980-368-3688",
            "photo": "https://lh3.googleusercontent.com/gps-cs-s/AHVAwerQBppSicUZB_FY9QszKNCP-JT4g9caD3ohCvoYaetLODy7GwTQZl93egw1jZpfNL6wPaVA_CTAEUjwLQT4ZDY7iFst5fR78Y7hfHGqkzUzbFOFLsJfTpwpdkq7JlHs2Te7rWlygK5orok=w800-h500-k-no",
            "photos_count": 7,
            "place_id": "ChIJ79I38fsdVIgRD0su4wT_zaw",
            "plus_code": "867X8763+XW",
            "popular_times": null,
            "postal_code": "28262",
            "posts": null,
            "prices": null,
            "query": "ChIJ79I38fsdVIgRD0su4wT_zaw",
            "range": null,
            "rating": null,
            "reservation_links": null,
            "reviews": null,
            "reviews_data": [],
            "reviews_id": null,
            "reviews_link": null,
            "reviews_per_score": null,
            "reviews_tags": null,
            "state": "North Carolina",
            "state_code": "NC",
            "street": "9211 N Tryon St #5",
            "street_view": "https://streetviewpixels-pa.googleapis.com/v1/thumbnail?panoid=oVF68STM6bhwkfmyu4mPbg&cb_client=search.gws-prod.gps&w=1600&h=1000&yaw=203.18007&pitch=0&thumbfov=100",
            "subtypes": "Vietnamese restaurant",
            "time_zone": "America/New_York",
            "type": "Vietnamese restaurant",
            "typical_time_spent": null,
            "verified": true,
            "website": "https://www.1368sweetcornercafe.com/",
            "working_hours": null,
            "working_hours_csv_compatible": null
        }
    },
    "photos": {
        "place_id": "ChIJ79I38fsdVIgRD0su4wT_zaw",
        "message": "Retrieved 1 photos, selected 1",
        "photo_urls": [
            "https://streetviewpixels-pa.googleapis.com/v1/thumbnail?panoid=oVF68STM6bhwkfmyu4mPbg&cb_client=maps_sv.tactile.gps&w=1600&h=1000&yaw=203.18007&pitch=0&thumbfov=100"
        ],
        "raw_data": {
            "about": {
                "Service options": {
                    "Delivery": true,
                    "Dine-in": true,
                    "No-contact delivery": true,
                    "Takeout": true
                }
            },
            "address": "9211 N Tryon St #5, Charlotte, NC 28262",
            "area_service": false,
            "booking_appointment_link": null,
            "business_status": "OPERATIONAL",
            "category": "restaurants",
            "cid": "12451888941205703439",
            "city": "Charlotte",
            "country": "United States of America",
            "country_code": "US",
            "county": "University City North",
            "description": null,
            "google_id": "0x88541dfbf137d2ef:0xaccdff04e32e4b0f",
            "h3": "8944dab5233ffff",
            "kgmid": "/g/11z11cy4y7",
            "latitude": 35.3123844,
            "located_google_id": null,
            "located_in": null,
            "location_link": "https://www.google.com/maps/place/1368+Sweet+Corner+Cafe/@35.3123844,-80.7452253,14z/data=!4m8!1m2!2m1!1s1368+Sweet+Corner+Cafe!3m4!1s0x88541dfbf137d2ef:0xaccdff04e32e4b0f!8m2!3d35.3123844!4d-80.7452253",
            "location_reviews_link": "https://www.google.com/maps/place/1368+Sweet+Corner+Cafe/@35.3123844,-80.7452253,13.99z/data=!4m16!1m7!3m6!1s0x88541dfbf137d2ef:0xaccdff04e32e4b0f!2s1368+Sweet+Corner+Cafe!8m2!3d35.3123844!4d-80.7452253!16s%2Fg%2F11ckvg1dmb!3m7!1s0x88541dfbf137d2ef:0xaccdff04e32e4b0f!8m2!3d35.3123844!4d-80.7452253!9m1!1b1!16s%2Fg%2F11ckvg1dmb?entry=ttu",
            "logo": "https://lh3.googleusercontent.com/-GInoYVGXTHc/AAAAAAAAAAI/AAAAAAAAAAA/vfeoF7DrtOQ/s44-p-k-no-ns-nd/photo.jpg",
            "longitude": -80.7452253,
            "menu_link": null,
            "name": "1368 Sweet Corner Cafe",
            "name_for_emails": "1368 Sweet Corner Cafe",
            "order_links": null,
            "other_hours": null,
            "owner_id": "112959749046836881640",
            "owner_link": "https://www.google.com/maps/contrib/112959749046836881640",
            "owner_title": "1368 Sweet Corner Cafe",
            "phone": "+1 980-368-3688",
            "photo": "https://lh3.googleusercontent.com/gps-cs-s/AHVAwerQBppSicUZB_FY9QszKNCP-JT4g9caD3ohCvoYaetLODy7GwTQZl93egw1jZpfNL6wPaVA_CTAEUjwLQT4ZDY7iFst5fR78Y7hfHGqkzUzbFOFLsJfTpwpdkq7JlHs2Te7rWlygK5orok=w800-h500-k-no",
            "photos_count": 7,
            "photos_data": [
                {
                    "latitude": 35.31248955366213,
                    "longitude": -80.74517012233886,
                    "original_photo_url": "https://streetviewpixels-pa.googleapis.com/v1/thumbnail?panoid=oVF68STM6bhwkfmyu4mPbg&cb_client=maps_sv.tactile.gps&w=203&h=100&yaw=203.18007&pitch=0&thumbfov=100",
                    "photo_date": "10/28/2022 13:00:00",
                    "photo_id": "oVF68STM6bhwkfmyu4mPbg",
                    "photo_source_video": null,
                    "photo_tag_ids": [
                        2
                    ],
                    "photo_tags": [
                        "front"
                    ],
                    "photo_upload_source": "launch",
                    "photo_url": "https://streetviewpixels-pa.googleapis.com/v1/thumbnail?panoid=oVF68STM6bhwkfmyu4mPbg&cb_client=maps_sv.tactile.gps&w=203&h=100&yaw=203.18007&pitch=0&thumbfov=100",
                    "photo_url_big": "https://streetviewpixels-pa.googleapis.com/v1/thumbnail?panoid=oVF68STM6bhwkfmyu4mPbg&cb_client=maps_sv.tactile.gps&w=1600&h=1000&yaw=203.18007&pitch=0&thumbfov=100"
                }
            ],
            "place_id": "ChIJ79I38fsdVIgRD0su4wT_zaw",
            "plus_code": "867X8763+XW",
            "popular_times": null,
            "postal_code": "28262",
            "posts": null,
            "prices": null,
            "query": "ChIJ79I38fsdVIgRD0su4wT_zaw",
            "range": null,
            "rating": null,
            "reservation_links": null,
            "reviews": null,
            "reviews_id": null,
            "reviews_link": null,
            "reviews_per_score": null,
            "reviews_tags": null,
            "state": "North Carolina",
            "state_code": "NC",
            "street": "9211 N Tryon St #5",
            "street_view": "https://streetviewpixels-pa.googleapis.com/v1/thumbnail?panoid=oVF68STM6bhwkfmyu4mPbg&cb_client=search.gws-prod.gps&w=1600&h=1000&yaw=203.18007&pitch=0&thumbfov=100",
            "subtypes": "Vietnamese restaurant",
            "time_zone": "America/New_York",
            "type": "Vietnamese restaurant",
            "typical_time_spent": null,
            "verified": true,
            "website": "https://www.1368sweetcornercafe.com/",
            "working_hours": null,
            "working_hours_csv_compatible": null
        }
    },
    "data_source": "OutscraperProvider",
    "last_updated": "2026-03-21T16:08:37.838125"
}